Verilog/Serial_paralel_converter/tester.v
module Probador (P_VALID, P_OUT, S_OUT, CLK, RESET, S_IN, P_IN, S_START);

// Se definen las entradas del modulo
input P_VALID, S_OUT;
input [31:0] P_OUT;

// Se definen las salidas del modulo
output reg CLK, RESET, S_IN, S_START; 
output reg [31:0] P_IN ;

initial begin
        // Se ponen las entradas en sus estados iniciales

        #1
        RESET = 1;
        S_START = 0; 

        #2
        RESET = 1;
        S_START = 1;
        P_IN = 32'b00000000000000001111111111111111;

        #1 
	S_IN <= 1;
        #1 
	S_IN <= 0;
        #1 
	S_IN <= 1;
        #1 
	S_IN <= 1;
        #1 
	S_IN <= 0;
        #1 
	S_IN <= 1;
        #1 
	S_IN <= 0;

       
        #1 
	S_IN <= 1;
        #1 
	S_IN <= 1;
        #1 
	S_IN <= 1;
        #1 
	S_IN <= 1;
        #1 
	S_IN <= 1;
        #1 
	S_IN <= 1;
        #1 
	S_IN <= 1;
        #1 
	S_IN <= 1;
        #1 
	S_IN <= 1;
        #1 
	S_IN <= 1;
        #1 
	S_IN <= 1;
        #1 
	S_IN <= 1;
        #1 
	S_IN = 1;
        #1 
	S_IN = 1;
        #1 
	S_IN = 1;
        #1 
	S_IN = 1;
        #1 
	S_IN = 1;
        #1 
	S_IN = 1;
        #1 
	S_IN = 1;
        #1 
	S_IN = 1;
        #1 
	S_IN = 1;
        #1 
	S_IN = 1;
        #1 
	S_IN = 1;
        #1 
	S_IN = 1;
        #1 
	S_IN = 1;
        #1 
	S_IN = 1;
        #1 
	S_IN = 1;
        #1 
	S_IN = 1;
        #1 
	S_IN = 1;
        #1 
	S_IN = 1;
        #1 
	S_IN = 1;
        #1 
	S_IN = 1;

        #35 
	RESET = 0;
     

        #10
        $finish;
        end

    initial	CLK <= 0;
    always 
        begin
        #1 CLK <= !CLK;
        end      
endmodule

Verilog/Serial_paralel_converter/paraleloaserie.v
module paraleloaserie (CLK, RESET, P_IN, S_START, S_OUT);

// Se definen las entradas del modulo
input  CLK, RESET, S_START;
input [31:0] P_IN;

// Se define la salida del modulo
output reg S_OUT; 

// Se define un contador para los ciclos
integer cont = 32;

// Se define el ciclo principal
always @(posedge CLK) begin
    // si reset es 1
    if (RESET == 1'b1) begin

        // Si S_START = 1 , cargar un bit de p_in en s_out
        if (S_START == 1'b1) begin
            S_OUT <= P_IN[cont]; 
            cont <=  cont - 1; 
           
        end
        // Para cualquier otro caso
        else if ((S_START == 1'b0)) begin
            S_OUT <= S_OUT;
        end
    end

    // Si reset es 0. todas las salidas son 0
    else if(RESET == 0)begin
        S_OUT <= 0;
    end
end
endmodule

Verilog/Serial_paralel_converter/maquina.v
module maquinadeestados (CLK, RESET, S_IN, conv);

// Definicion de entradas y salidas
input CLK, RESET, S_IN;
output reg conv;

// Registros donde se guardan los valores de lso estados actual y siguiente
reg [7:0] state;
reg [7:0] nxt_state;           

// Definicion de FF                 
always @(posedge CLK) begin
  if (~RESET) begin
    // Estado IDLE
    state  <= 8'b00000001;
    conv = 1'b0;
  end else begin
 // Definición de lo que pasa en las salidas
    state  <= nxt_state;
    conv <= 1'b1;
  end
end

// Logica combinacional - Estados
always @(*) begin

// Comportamiento de la maquina de estados
// Define las transiciones de proximo estado

  case(state)
    8'b00000001: if (S_IN) begin         // Si S_IN=1 se pasa al siguiente estado 
                  nxt_state = 8'b00000010;
                  conv = 1'b0;
                end
                         
    8'b00000010: begin			// Si S_IN=0 se pasa al siguiente estado
                 if (~S_IN) begin 
                  nxt_state = 8'b00000100; 
                  conv = 1'b0;  
                 end
                 else nxt_state = 8'b00000010;	// Si S_IN=1 nos quedamos en este codigo                                                        
                 end

    8'b00000100: begin			// Cuando S_IN=1 se pasa al siguiente estado 
                 if (S_IN) begin
                  nxt_state = 8'b00001000;
                  conv = 1'b0;
                 end   
                 else nxt_state = 8'b00000001; // Cuando S_IN=0 se devuelve al IDLE
                 end 
           
    8'b00001000: begin			//Se pasa al siguiente estado con S_IN=1                     
                 if (S_IN) begin
                  nxt_state = 8'b00010000;
                  conv = 1'b0;
                 end
                 else nxt_state = 8'b00000100; //Se devuelve al estado anterior
               end
               
    8'b00010000: begin			//Se pasa al sigueinte estado con S_IN=0                             
                 if (~S_IN) begin 
                  nxt_state = 8'b00100000;
                  conv = 1'b0;
                 end
                 else nxt_state = 8'b00000010; //Se devuelve al estado 10
               end     

    8'b00100000: begin			//Se pasa al siguiente estado con S_IN=1                             
                 if (S_IN) begin
                  nxt_state = 8'b01000000;
                  conv = 1'b0;
                 end
                 else nxt_state = 8'b00000001; //Con S_IN=0 se va al IDLE
               end 

    8'b01000000: begin			//S_IN = 0 se pasa al siguiente estado                             
                 if (~S_IN) begin
                  nxt_state = 8'b10000000;
                  conv = 1'b0;
                 end
                 else nxt_state = 8'b00010000; //S_IN=1 se devuelve al estado 10000
               end                                                                           
               
    8'b10000000: begin			//Caracter de entrada recibo
                 conv = 1'b1;                      
                 if (~RESET) nxt_state = 8'b00000001; //Conve = 1
               end

    // Si la maquina entrara en un estado inesperado, regrese al inicio
    default:   nxt_state = 8'b00000001;
  endcase

end
endmodule

Verilog/Serial_paralel_converter/serieaparalelo.v
`include "maquina.v"
module serieaparalelo (CLK, RESET, S_IN, P_OUT, P_VALID);
 // Entradas del modulo
    input CLK, RESET, S_IN;

 // Salidas del modulo
    output reg P_VALID;
    output reg [31:0] P_OUT; 

//Conexiones con maquina 

    wire CLK, RESET, S_IN, conver_ON ;

    // Se guarda el indice del registro y el contador respectivamente
    integer cont = 32 ;
    
    // Se instancia la maquina de estados pata obtener el caracter de inicio 0x5A
    maquinadeestados conv (
    .RESET  (RESET),
    .S_IN  (S_IN),
    .CLK    (CLK),
    .conv  (conver_ON));

    // Se define el ciclo principal 
    always @(posedge CLK) begin 

        if (RESET == 1) begin

 // Si se detecta 0x5A en la entrada serial
            if (conver_ON == 1)begin
                // Se asigna a p_out el valor de s_in en el bit correspondiente
                P_OUT[cont] <=  S_IN;
                cont <= cont - 1;

 //Transmisión incompleta de los 32 bits
                if(cont != 0 )begin
                    P_VALID = 1'b0;
                end
            
 //Se activa  P_VALID = 1
                else begin
                P_VALID <= 1'b1;
                end
            end
        end
 //Si se pone RESET = 0, todas las salidas se ponen en 0
        else if (RESET == 0) begin
            P_OUT [31:0] = 32'b0; 
            P_VALID = 1'b0; 
        end
    end
endmodule

Verilog/Serial_paralel_converter/convertidor_sp_ps.v
`include "serieaparalelo.v"
`include "paraleloaserie.v"

module convertidor (CLK, RESET, S_IN, P_IN, S_START, P_VALID, P_OUT, S_OUT);

// Se definen las entradas del modulo
input CLK, RESET, S_IN, S_START; 
input [31:0] P_IN ;

// Se definen las salidas del modulo
output wire P_VALID, S_OUT;
output wire [31:0] P_OUT;  

// Se instancia el modulo que convierte de serie a paralelo
serieaparalelo SP(
    .CLK      (CLK),
    .RESET    (RESET),
    .S_IN     (S_IN),
    .P_OUT    (P_OUT),
    .P_VALID  (P_VALID)
);

// Se instancia el modulo que convierte de paralelo a serie
paraleloaserie PS(
    .CLK      (CLK),
    .RESET    (RESET),
    .P_IN     (P_IN),
    .S_START  (S_START),
    .S_OUT    (S_OUT)
);

endmodule

Verilog/Serial_paralel_converter/testbench.v
`include "convertidor_sp_ps.v"
`include "tester.v"

// Se define un modulo para el banco de pruebas

module testbench;

// Las senales se definen como cables
wire CLK, RESET, S_IN, S_START, P_VALID, S_OUT;
wire [31:0] P_OUT, P_IN; 

// Se ctrea una instancia del convertidor

convertidor convertidorINST(
    .CLK      (CLK),
    .RESET    (RESET),
    .S_IN     (S_IN),
    .P_IN     (P_IN),
    .S_START  (S_START),
    .P_VALID  (P_VALID),
    .P_OUT    (P_OUT),
    .S_OUT    (S_OUT)    
);

// Se crea una instancia del probador

Probador probadorINST(
    .CLK      (CLK),
    .RESET    (RESET),
    .S_IN     (S_IN),
    .P_IN     (P_IN),
    .S_START  (S_START),
    .P_VALID  (P_VALID),
    .P_OUT    (P_OUT),
    .S_OUT    (S_OUT)    
);

// Se genera el display para cuando se corra el comando vvp y el archivo .vcd para GTKWave
initial begin
    $dumpfile ("convertidorspps.vcd");
    $dumpvars;
    $display("\t\t\tCLK\| RESET| S_IN |     \tP_OUT                            | P_VALID|S_START|     P_IN                             | S_OUT");
    $display("\t\t\t---------------------------------------------------------------------------------------------------------------------------");
    $monitor( $time, "|\t%b |\t%b |\t%b |\t%b |\t%b |\t%b |\t%b |\t%b", CLK, RESET, S_IN, P_OUT, P_VALID, S_START, P_IN, S_OUT);
    end
    endmodule

Verilog/Serial_paralel_converter/convertidorspps.vcd
$date
	Thu Aug 17 15:58:57 2023
$end
$version
	Icarus Verilog
$end
$timescale
	1s
$end
$scope module testbench $end
$var wire 1 ! S_START $end
$var wire 1 " S_OUT $end
$var wire 1 # S_IN $end
$var wire 1 $ RESET $end
$var wire 1 % P_VALID $end
$var wire 32 & P_OUT [31:0] $end
$var wire 32 ' P_IN [31:0] $end
$var wire 1 ( CLK $end
$scope module convertidorINST $end
$var wire 1 ! S_START $end
$var wire 1 " S_OUT $end
$var wire 1 # S_IN $end
$var wire 1 $ RESET $end
$var wire 1 % P_VALID $end
$var wire 32 ) P_OUT [31:0] $end
$var wire 32 * P_IN [31:0] $end
$var wire 1 ( CLK $end
$scope module PS $end
$var wire 1 ! S_START $end
$var wire 1 $ RESET $end
$var wire 32 + P_IN [31:0] $end
$var wire 1 ( CLK $end
$var reg 1 " S_OUT $end
$var integer 32 , cont [31:0] $end
$upscope $end
$scope module SP $end
$var wire 1 - conver_ON $end
$var wire 1 # S_IN $end
$var wire 1 $ RESET $end
$var wire 1 ( CLK $end
$var reg 32 . P_OUT [31:0] $end
$var reg 1 % P_VALID $end
$var integer 32 / cont [31:0] $end
$scope module conv $end
$var wire 1 # S_IN $end
$var wire 1 $ RESET $end
$var wire 1 ( CLK $end
$var reg 1 - conv $end
$var reg 8 0 nxt_state [7:0] $end
$var reg 8 1 state [7:0] $end
$upscope $end
$upscope $end
$upscope $end
$scope module probadorINST $end
$var wire 32 2 P_OUT [31:0] $end
$var wire 1 % P_VALID $end
$var wire 1 " S_OUT $end
$var reg 1 ( CLK $end
$var reg 32 3 P_IN [31:0] $end
$var reg 1 $ RESET $end
$var reg 1 # S_IN $end
$var reg 1 ! S_START $end
$upscope $end
$upscope $end
$enddefinitions $end
#0
$dumpvars
bx 3
bx 2
bx 1
bx 0
b100000 /
bx .
x-
b100000 ,
bx +
bx *
bx )
0(
bx '
bx &
x%
x$
x#
x"
x!
$end
#1
1-
b1 1
1(
b1 0
0!
1$
#2
0(
#3
b11111 ,
b11111 /
0%
1(
b1111111111111111 '
b1111111111111111 *
b1111111111111111 +
b1111111111111111 3
1!
#4
0-
b10 0
0(
1#
#5
b100 0
0-
b10 1
b11110 ,
0"
1(
0#
#6
b10 0
0(
1#
#7
b11101 ,
1-
1(
#8
0-
b100 0
0(
0#
#9
1-
b11100 ,
b10 0
1(
1#
#10
0-
b100 0
0(
0#
#11
b11011 ,
1-
b10 0
1(
1#
#12
0(
#13
b11110 /
b1xxxxxxxxxxxxxxxxxxxxxxxxxxxxxxx &
b1xxxxxxxxxxxxxxxxxxxxxxxxxxxxxxx )
b1xxxxxxxxxxxxxxxxxxxxxxxxxxxxxxx .
b1xxxxxxxxxxxxxxxxxxxxxxxxxxxxxxx 2
b11010 ,
1(
#14
0(
#15
b11001 ,
b11101 /
b11xxxxxxxxxxxxxxxxxxxxxxxxxxxxxx &
b11xxxxxxxxxxxxxxxxxxxxxxxxxxxxxx )
b11xxxxxxxxxxxxxxxxxxxxxxxxxxxxxx .
b11xxxxxxxxxxxxxxxxxxxxxxxxxxxxxx 2
1(
#16
0(
#17
b11100 /
b111xxxxxxxxxxxxxxxxxxxxxxxxxxxxx &
b111xxxxxxxxxxxxxxxxxxxxxxxxxxxxx )
b111xxxxxxxxxxxxxxxxxxxxxxxxxxxxx .
b111xxxxxxxxxxxxxxxxxxxxxxxxxxxxx 2
b11000 ,
1(
#18
0(
#19
b10111 ,
b11011 /
b1111xxxxxxxxxxxxxxxxxxxxxxxxxxxx &
b1111xxxxxxxxxxxxxxxxxxxxxxxxxxxx )
b1111xxxxxxxxxxxxxxxxxxxxxxxxxxxx .
b1111xxxxxxxxxxxxxxxxxxxxxxxxxxxx 2
1(
#20
0(
#21
b11010 /
b11111xxxxxxxxxxxxxxxxxxxxxxxxxxx &
b11111xxxxxxxxxxxxxxxxxxxxxxxxxxx )
b11111xxxxxxxxxxxxxxxxxxxxxxxxxxx .
b11111xxxxxxxxxxxxxxxxxxxxxxxxxxx 2
b10110 ,
1(
#22
0(
#23
b10101 ,
b11001 /
b111111xxxxxxxxxxxxxxxxxxxxxxxxxx &
b111111xxxxxxxxxxxxxxxxxxxxxxxxxx )
b111111xxxxxxxxxxxxxxxxxxxxxxxxxx .
b111111xxxxxxxxxxxxxxxxxxxxxxxxxx 2
1(
#24
0(
#25
b11000 /
b1111111xxxxxxxxxxxxxxxxxxxxxxxxx &
b1111111xxxxxxxxxxxxxxxxxxxxxxxxx )
b1111111xxxxxxxxxxxxxxxxxxxxxxxxx .
b1111111xxxxxxxxxxxxxxxxxxxxxxxxx 2
b10100 ,
1(
#26
0(
#27
b10011 ,
b10111 /
b11111111xxxxxxxxxxxxxxxxxxxxxxxx &
b11111111xxxxxxxxxxxxxxxxxxxxxxxx )
b11111111xxxxxxxxxxxxxxxxxxxxxxxx .
b11111111xxxxxxxxxxxxxxxxxxxxxxxx 2
1(
#28
0(
#29
b10110 /
b111111111xxxxxxxxxxxxxxxxxxxxxxx &
b111111111xxxxxxxxxxxxxxxxxxxxxxx )
b111111111xxxxxxxxxxxxxxxxxxxxxxx .
b111111111xxxxxxxxxxxxxxxxxxxxxxx 2
b10010 ,
1(
#30
0(
#31
b10001 ,
b10101 /
b1111111111xxxxxxxxxxxxxxxxxxxxxx &
b1111111111xxxxxxxxxxxxxxxxxxxxxx )
b1111111111xxxxxxxxxxxxxxxxxxxxxx .
b1111111111xxxxxxxxxxxxxxxxxxxxxx 2
1(
#32
0(
#33
b10100 /
b11111111111xxxxxxxxxxxxxxxxxxxxx &
b11111111111xxxxxxxxxxxxxxxxxxxxx )
b11111111111xxxxxxxxxxxxxxxxxxxxx .
b11111111111xxxxxxxxxxxxxxxxxxxxx 2
b10000 ,
1(
#34
0(
#35
b1111 ,
b10011 /
b111111111111xxxxxxxxxxxxxxxxxxxx &
b111111111111xxxxxxxxxxxxxxxxxxxx )
b111111111111xxxxxxxxxxxxxxxxxxxx .
b111111111111xxxxxxxxxxxxxxxxxxxx 2
1(
#36
0(
#37
b10010 /
b1111111111111xxxxxxxxxxxxxxxxxxx &
b1111111111111xxxxxxxxxxxxxxxxxxx )
b1111111111111xxxxxxxxxxxxxxxxxxx .
b1111111111111xxxxxxxxxxxxxxxxxxx 2
b1110 ,
1"
1(
#38
0(
#39
b1101 ,
b10001 /
b11111111111111xxxxxxxxxxxxxxxxxx &
b11111111111111xxxxxxxxxxxxxxxxxx )
b11111111111111xxxxxxxxxxxxxxxxxx .
b11111111111111xxxxxxxxxxxxxxxxxx 2
1(
#40
0(
#41
b10000 /
b111111111111111xxxxxxxxxxxxxxxxx &
b111111111111111xxxxxxxxxxxxxxxxx )
b111111111111111xxxxxxxxxxxxxxxxx .
b111111111111111xxxxxxxxxxxxxxxxx 2
b1100 ,
1(
#42
0(
#43
b1011 ,
b1111 /
b1111111111111111xxxxxxxxxxxxxxxx &
b1111111111111111xxxxxxxxxxxxxxxx )
b1111111111111111xxxxxxxxxxxxxxxx .
b1111111111111111xxxxxxxxxxxxxxxx 2
1(
#44
0(
#45
b1110 /
b11111111111111111xxxxxxxxxxxxxxx &
b11111111111111111xxxxxxxxxxxxxxx )
b11111111111111111xxxxxxxxxxxxxxx .
b11111111111111111xxxxxxxxxxxxxxx 2
b1010 ,
1(
#46
0(
#47
b1001 ,
b1101 /
b111111111111111111xxxxxxxxxxxxxx &
b111111111111111111xxxxxxxxxxxxxx )
b111111111111111111xxxxxxxxxxxxxx .
b111111111111111111xxxxxxxxxxxxxx 2
1(
#48
0(
#49
b1100 /
b1111111111111111111xxxxxxxxxxxxx &
b1111111111111111111xxxxxxxxxxxxx )
b1111111111111111111xxxxxxxxxxxxx .
b1111111111111111111xxxxxxxxxxxxx 2
b1000 ,
1(
#50
0(
#51
b111 ,
b1011 /
b11111111111111111111xxxxxxxxxxxx &
b11111111111111111111xxxxxxxxxxxx )
b11111111111111111111xxxxxxxxxxxx .
b11111111111111111111xxxxxxxxxxxx 2
1(
#52
0(
#53
b1010 /
b111111111111111111111xxxxxxxxxxx &
b111111111111111111111xxxxxxxxxxx )
b111111111111111111111xxxxxxxxxxx .
b111111111111111111111xxxxxxxxxxx 2
b110 ,
1(
#54
0(
#55
b101 ,
b1001 /
b1111111111111111111111xxxxxxxxxx &
b1111111111111111111111xxxxxxxxxx )
b1111111111111111111111xxxxxxxxxx .
b1111111111111111111111xxxxxxxxxx 2
1(
#56
0(
#57
b1000 /
b11111111111111111111111xxxxxxxxx &
b11111111111111111111111xxxxxxxxx )
b11111111111111111111111xxxxxxxxx .
b11111111111111111111111xxxxxxxxx 2
b100 ,
1(
#58
0(
#59
b11 ,
b111 /
b111111111111111111111111xxxxxxxx &
b111111111111111111111111xxxxxxxx )
b111111111111111111111111xxxxxxxx .
b111111111111111111111111xxxxxxxx 2
1(
#60
0(
#61
b110 /
b1111111111111111111111111xxxxxxx &
b1111111111111111111111111xxxxxxx )
b1111111111111111111111111xxxxxxx .
b1111111111111111111111111xxxxxxx 2
b10 ,
1(
#62
0(
#63
b1 ,
b101 /
b11111111111111111111111111xxxxxx &
b11111111111111111111111111xxxxxx )
b11111111111111111111111111xxxxxx .
b11111111111111111111111111xxxxxx 2
1(
#64
0(
#65
b100 /
b111111111111111111111111111xxxxx &
b111111111111111111111111111xxxxx )
b111111111111111111111111111xxxxx .
b111111111111111111111111111xxxxx 2
b0 ,
1(
#66
0(
#67
b11111111111111111111111111111111 ,
b11 /
b1111111111111111111111111111xxxx &
b1111111111111111111111111111xxxx )
b1111111111111111111111111111xxxx .
b1111111111111111111111111111xxxx 2
1(
#68
0(
#69
b10 /
b11111111111111111111111111111xxx &
b11111111111111111111111111111xxx )
b11111111111111111111111111111xxx .
b11111111111111111111111111111xxx 2
b11111111111111111111111111111110 ,
x"
1(
#70
0(
#71
b11111111111111111111111111111101 ,
b1 /
b111111111111111111111111111111xx &
b111111111111111111111111111111xx )
b111111111111111111111111111111xx .
b111111111111111111111111111111xx 2
1(
#72
0(
#73
b0 /
b1111111111111111111111111111111x &
b1111111111111111111111111111111x )
b1111111111111111111111111111111x .
b1111111111111111111111111111111x 2
b11111111111111111111111111111100 ,
1(
#74
0(
#75
b11111111111111111111111111111011 ,
1%
b11111111111111111111111111111111 /
b11111111111111111111111111111111 &
b11111111111111111111111111111111 )
b11111111111111111111111111111111 .
b11111111111111111111111111111111 2
1(
#76
0(
#77
b1 1
0"
0-
0%
b0 &
b0 )
b0 .
b0 2
1(
0$
