Verilog/Serial_paralel_converter/Enhanced_Serial_Paralel/TESTER.v
module TESTER(
    input P_VALID,
    input S_OUT,
    input [31:0] P_OUT,
    output reg CLK,
    output reg RESET,
    output reg S_START,
    output reg S_IN,
    output reg [31:0] P_IN
);

// CLK generator
initial begin
    CLK = 0;
end
always begin
    #1 CLK <= !CLK;
end


// TEST
initial begin
    // Display
    $dumpfile("seriestoparalel.vcd");
    $dumpvars(0, testbench); 
    $display("\t\t------------------------------------------");
    $display("\t\tTime\| CLK \|  S_START  \|  S_IN \|  S_OUT  \| P_OUT");
    $display("\t\t------------------------------------------");
    $monitor( $time, "|\t%b |\t%b |\t%b |\t%b |\t%b ", CLK, S_START, S_IN, S_OUT, P_OUT);

    RESET = 0;
    S_START = 0;   
    #2
    RESET = 1;
    #2
    // Paralel to series
    S_START = 1;
    P_IN = 32'b00000000000000001111111111111111;
    #64
    RESET = 0;
    // Series to paralel
    #1 
	S_IN <= 1;
    #1 
	S_IN <= 0;
    #1 
	S_IN <= 1;
    // Test de FSM en medio de 0X5A
    #1 
	S_IN <= 0;
    #1 
	S_IN <= 1;
    #1 
	S_IN <= 0;
    #1 
	S_IN <= 1;
    #1 
	S_IN <= 0;
    // Word of confirmation
    // Two PERIODS
    #4
	S_IN <= 1;
    #1 
	S_IN <= 0;
    #1 
	S_IN <= 1;
    #1 
	S_IN <= 0;
    #1 
	S_IN <= 1;
    #1 
	S_IN <= 0;
    #1 
	S_IN <= 1;
    #1 
	S_IN <= 0;
    #1 
	S_IN <= 1;
    #1 
	S_IN <= 0;
    #1 
	S_IN <= 1;
    #1 
	S_IN <= 0;
    #1 
	S_IN <= 1;
    #1 
	S_IN <= 0;
    #1 
	S_IN <= 1;
    #1 
	S_IN <= 0;
    #1 
    S_IN <= 1;
    #1 
	S_IN <= 0;
    #1 
	S_IN <= 1;
    #1 
	S_IN <= 0;
    #1 
	S_IN <= 1;
    #1 
	S_IN <= 0;
    #1 
	S_IN <= 1;
    #1 
	S_IN <= 0;
    #1 
	S_IN <= 1;
    #1 
	S_IN <= 0;
    #1 
	S_IN <= 1;
    #1 
	S_IN <= 0;
    #1 
	S_IN <= 1;
    #1 
	S_IN <= 0;
    #1 
	S_IN <= 1;
    #1 
	S_IN <= 0;

    #150
    RESET = 0;
    #5
    $finish;
end
endmodule

Verilog/Serial_paralel_converter/Enhanced_Serial_Paralel/paraleltoseries.v
module paraleltoseries(
    input CLK,
    input RESET,
    input S_START,
    input [31:0] P_IN,
    output reg S_OUT
);

// Counter to add S_OUT=P_IN[count]
integer cont = 31;

always @(posedge CLK) begin
    if (RESET) begin
        if (S_START) begin 
            // Serial out
            S_OUT <= P_IN[cont];
            // Update counter
            cont <= cont - 1;
        end else begin
            S_OUT <= S_OUT;
        end
    end else begin
        // 0 out
        S_OUT <= 0;
    end
end
endmodule

Verilog/Serial_paralel_converter/Enhanced_Serial_Paralel/FSM.v
// TO start the serial to paralel is necesary a code: 0x5A
module FSM(
    input CLK,
    input S_IN,
    input RESET,
    output reg CONVERTION
);

// FSM states
reg [7:0] state;
reg [7:0] nxt_state;           


// 0x5A:01011010

always @(posedge CLK ) begin
    if (RESET) begin
        // Inicia en IDLE
        state <= 8'b00000001;
        case(state)
            8'b00000001: if (S_IN) begin
                nxt_state = 8'b00000001;
                CONVERTION = 1'b0;
            end else begin
                nxt_state = 8'b00000010;
                CONVERTION = 1'b0;
            end
            8'b00000010: if (S_IN) begin
                nxt_state = 8'b00000101;
                CONVERTION = 1'b0;
            end else begin
                nxt_state = 8'b00000010;
                CONVERTION = 1'b0;               
            end
            8'b00000101: if (S_IN) begin
                nxt_state = 8'b00001011;
                CONVERTION = 1'b0;
            end else begin
                nxt_state = 8'b00000101;
                CONVERTION = 1'b0;
            end
            8'b00001011: if (S_IN) begin
                nxt_state = 8'b00001011;
                CONVERTION = 1'b0;
            end else begin
                nxt_state = 8'b00010110;
                CONVERTION = 1'b0;                
            end
            8'b00010110: if (S_IN) begin
                nxt_state = 8'b00101101;
                CONVERTION = 1'b0;
            end else begin
                nxt_state = 8'b00010110;
                CONVERTION = 1'b0;                
            end
            8'b00101101: if (S_IN) begin
                nxt_state = 8'b00101101;
                CONVERTION = 1'b0;
            end else begin
                nxt_state = 8'b01011010;
                CONVERTION = 1'b0;                
            end
            8'b01011010: begin
                // Caracter de entrada recibido
                CONVERTION = 1'b1;
            end
            default:   nxt_state = 8'b00000001;
        endcase
    end else begin
        state <= nxt_state;
    end
end


endmodule

Verilog/Serial_paralel_converter/Enhanced_Serial_Paralel/seriestoparalel.v
`include "FSM.v"
module seriestoparalel(
    input CLK,
    input RESET,
    input S_IN,
    output reg P_VALID,
    output reg [31:0] P_OUT 
); 

// Signal from FSM
wire CONVERTION_ON;
// Counter to validate transaction
integer cont = 31;

FSM maquina(
    .CLK(CLK),
    .S_IN(S_IN),
    .RESET(RESET),
    .CONVERTION(CONVERTION_ON)
);

always @(posedge CLK ) begin
    if (RESET) begin
        if (CONVERTION_ON) begin
            // Full transaction compleated
            if (cont == 0) begin
                P_VALID <= 1;
                P_OUT <= P_OUT;
            end else begin
                P_VALID <= 0;
            end
            //Append to reg
            P_OUT[cont] <= S_IN;
            // Update counter
            cont <= cont - 1;            
        end
    end else begin
        P_OUT <= 32'b0;
        P_VALID <= 1'b0;
    end
end

endmodule

Verilog/Serial_paralel_converter/Enhanced_Serial_Paralel/SERIES_PARALEL_Converter.v
`include "seriestoparalel.v"
`include "paraleltoseries.v"

module CONVERTER(
    input CLK, 
    input RESET, 
    input S_START, 
    input S_IN,
    input [31:0] P_IN,
    output wire P_VALID, S_OUT,
    output wire [31:0] P_OUT
);

// Instance

seriestoparalel SP(
    .CLK (CLK),
    .RESET (RESET),
    .S_IN (S_IN),
    .P_VALID (P_VALID),
    .P_OUT (P_OUT)
);

paraleltoseries PS(
    .CLK (CLK),
    .RESET (RESET),
    .S_START (S_START),
    .P_IN (P_IN),
    .S_OUT (S_OUT)
);

endmodule

Verilog/Serial_paralel_converter/Enhanced_Serial_Paralel/TESTBENCH.v
`include "SERIES_PARALEL_Converter.v"
`include "TESTER.v"

module testbench;

wire CLK;
wire RESET;
wire S_START;
wire S_IN;
wire [31:0] P_IN;
wire P_VALID;
wire S_OUT;
wire [31:0] P_OUT;

CONVERTER CONVERTER1(
    .CLK(CLK),
    .RESET(RESET),
    .S_START(S_START),
    .S_IN(S_IN),
    .P_IN(P_IN),
    .P_VALID(P_VALID),
    .S_OUT(S_OUT),
    .P_OUT(P_OUT)
);

TESTER TESTER1(
    .CLK(CLK),
    .RESET(RESET),
    .S_START(S_START),
    .S_IN(S_IN),
    .P_IN(P_IN),
    .P_VALID(P_VALID),
    .S_OUT(S_OUT),
    .P_OUT(P_OUT)
);
endmodule

Verilog/Serial_paralel_converter/Enhanced_Serial_Paralel/seriestoparalel.vcd
$date
	Sun Mar 16 18:36:43 2025
$end
$version
	Icarus Verilog
$end
$timescale
	1s
$end
$scope module testbench $end
$var wire 1 ! S_START $end
$var wire 1 " S_OUT $end
$var wire 1 # S_IN $end
$var wire 1 $ RESET $end
$var wire 1 % P_VALID $end
$var wire 32 & P_OUT [31:0] $end
$var wire 32 ' P_IN [31:0] $end
$var wire 1 ( CLK $end
$scope module CONVERTER1 $end
$var wire 1 ! S_START $end
$var wire 1 " S_OUT $end
$var wire 1 # S_IN $end
$var wire 1 $ RESET $end
$var wire 1 % P_VALID $end
$var wire 32 ) P_OUT [31:0] $end
$var wire 32 * P_IN [31:0] $end
$var wire 1 ( CLK $end
$scope module PS $end
$var wire 1 ! S_START $end
$var wire 1 $ RESET $end
$var wire 32 + P_IN [31:0] $end
$var wire 1 ( CLK $end
$var reg 1 " S_OUT $end
$var integer 32 , cont [31:0] $end
$upscope $end
$scope module SP $end
$var wire 1 # S_IN $end
$var wire 1 $ RESET $end
$var wire 1 - CONVERTION_ON $end
$var wire 1 ( CLK $end
$var reg 32 . P_OUT [31:0] $end
$var reg 1 % P_VALID $end
$var integer 32 / cont [31:0] $end
$scope module maquina $end
$var wire 1 # S_IN $end
$var wire 1 $ RESET $end
$var wire 1 ( CLK $end
$var reg 1 - CONVERTION $end
$var reg 8 0 nxt_state [7:0] $end
$var reg 8 1 state [7:0] $end
$upscope $end
$upscope $end
$upscope $end
$scope module TESTER1 $end
$var wire 32 2 P_OUT [31:0] $end
$var wire 1 % P_VALID $end
$var wire 1 " S_OUT $end
$var reg 1 ( CLK $end
$var reg 32 3 P_IN [31:0] $end
$var reg 1 $ RESET $end
$var reg 1 # S_IN $end
$var reg 1 ! S_START $end
$upscope $end
$upscope $end
$enddefinitions $end
#0
$dumpvars
bx 3
bx 2
bx 1
bx 0
b11111 /
bx .
x-
b11111 ,
bx +
bx *
bx )
0(
bx '
bx &
x%
0$
x#
x"
0!
$end
#1
0%
b0 &
b0 )
b0 .
b0 2
0"
1(
#2
0(
1$
#3
b1 1
b1 0
1(
#4
0(
b1111111111111111 '
b1111111111111111 *
b1111111111111111 +
b1111111111111111 3
1!
#5
b11110 ,
0-
b10 0
1(
#6
0(
#7
b11101 ,
1(
#8
0(
#9
b11100 ,
1(
#10
0(
#11
b11011 ,
1(
#12
0(
#13
b11010 ,
1(
#14
0(
#15
b11001 ,
1(
#16
0(
#17
b11000 ,
1(
#18
0(
#19
b10111 ,
1(
#20
0(
#21
b10110 ,
1(
#22
0(
#23
b10101 ,
1(
#24
0(
#25
b10100 ,
1(
#26
0(
#27
b10011 ,
1(
#28
0(
#29
b10010 ,
1(
#30
0(
#31
b10001 ,
1(
#32
0(
#33
b10000 ,
1(
#34
0(
#35
b1111 ,
1(
#36
0(
#37
b1110 ,
1"
1(
#38
0(
#39
b1101 ,
1(
#40
0(
#41
b1100 ,
1(
#42
0(
#43
b1011 ,
1(
#44
0(
#45
b1010 ,
1(
#46
0(
#47
b1001 ,
1(
#48
0(
#49
b1000 ,
1(
#50
0(
#51
b111 ,
1(
#52
0(
#53
b110 ,
1(
#54
0(
#55
b101 ,
1(
#56
0(
#57
b100 ,
1(
#58
0(
#59
b11 ,
1(
#60
0(
#61
b10 ,
1(
#62
0(
#63
b1 ,
1(
#64
0(
#65
b0 ,
1(
#66
0(
#67
b11111111111111111111111111111111 ,
1(
#68
0(
0$
#69
b10 1
0"
1(
1#
#70
0(
0#
#71
1(
1#
#72
0(
0#
#73
1(
1#
#74
0(
0#
#75
1(
1#
#76
0(
0#
#77
1(
#78
0(
#79
1(
#80
0(
1#
#81
1(
0#
#82
0(
1#
#83
1(
0#
#84
0(
1#
#85
1(
0#
#86
0(
1#
#87
1(
0#
#88
0(
1#
#89
1(
0#
#90
0(
1#
#91
1(
0#
#92
0(
1#
#93
1(
0#
#94
0(
1#
#95
1(
0#
#96
0(
1#
#97
1(
0#
#98
0(
1#
#99
1(
0#
#100
0(
1#
#101
1(
0#
#102
0(
1#
#103
1(
0#
#104
0(
1#
#105
1(
0#
#106
0(
1#
#107
1(
0#
#108
0(
1#
#109
1(
0#
#110
0(
1#
#111
1(
0#
