Verilog/MDIO_transaction_generator/testlectura.v
module testerlectura(CLK, MDC, RESET, MDIO_START, MDIO_OUT, MDIO_OE, MDIO_IN, T_DATA, RD_DATA, DATA_RDY);

//Entradas
output reg CLK, RESET, MDIO_START, MDIO_IN;
output reg [31:0] T_DATA;

//Salida
input wire [15:0] RD_DATA;
input wire DATA_RDY, MDC, MDIO_OE, MDIO_OUT;

//Reloj
        always #2 CLK = ~CLK;
//Valores de testbench
integer i=0, seed;

initial begin
        $dumpfile("testMDIO.vcd");
        $dumpvars();
//Valores iniciales
        CLK <= 1;
        RESET <= 0;
        #5
        RESET <= 1;
        MDIO_START <= 1;
        T_DATA <= 32'h0x61115F1F; //Valor de prueba que indica lectura
        for (i=0;i<70;i=i+1)begin
                #3 seed = $urandom%2;
                MDIO_IN = seed;
        end
        #100;
        RESET <= 0;
        #20;

        $finish;
end

endmodule

Verilog/MDIO_transaction_generator/generadortrans_MDIO.v
module mdio(CLK,MDC, RESET, MDIO_START, MDIO_OUT, MDIO_OE, MDIO_IN, T_DATA, RD_DATA, DATA_RDY);

//Entradas
input wire CLK, RESET, MDIO_START, MDIO_IN;
input wire [31:0] T_DATA;

//Salidas
output reg [15:0] RD_DATA;
output reg DATA_RDY, MDC, MDIO_OE, MDIO_OUT;

//Variables internas
reg [5:0] count; //Contador para mitad de frecuencia
reg [5:0] nxt_count;
reg [15:0] nxt_RD_DATA; //Contador para saber valores contenidos en RD_DATA
reg nxt_DATA_RDY, nxt_MDC, nxt_MDIO_OE, nxt_MDIO_OUT;

//Clock divider

always @(posedge CLK)begin
        if(RESET == 0)begin
                MDC <= 0;
        end else begin
                MDC <= !MDC;
        end
end

//Definición de siguientes valores en cada MDC up 
always @(posedge MDC)begin
        count <= nxt_count;
        DATA_RDY <= nxt_DATA_RDY;
        MDIO_OE <= nxt_MDIO_OE;
        MDIO_OUT <= nxt_MDIO_OUT;
        RD_DATA[15:0] <= nxt_RD_DATA;
end

//Contador para transmisión de datos seriales
always @(posedge MDIO_START)begin
        count <= 31;
end


always @(*)begin
	//Valores iniciales
        nxt_count = count;
        nxt_DATA_RDY = 0;
        nxt_MDIO_OE = 0;
        nxt_MDIO_OUT = 0;
        nxt_RD_DATA[15:0] = RD_DATA[15:0];

        if(MDIO_START == 1 && count >= 0)begin
	
//Caso de escritura
        nxt_MDIO_OUT = T_DATA[count];  //Transacción de paralelo a serie
        if(count!=0)begin
                nxt_count = count - 1; //Contador ubica valores desde el bit más significativo
        end
        else begin
                nxt_count = count;     //Mantiene el valor que se pasa al flipflop
        end
        if(T_DATA[29:28]==2'b10 && count>15)begin //En lectura se mantiene señal en alto en primeros 16 bits
                nxt_MDIO_OE = 1;
        end
        else if (T_DATA[29:28]==2'b01)begin //En escritura se mantiene en alto en los 32 bits
                nxt_MDIO_OE = 1;
        end
        else begin
                nxt_MDIO_OE = 0;	//Luego de los 16 bits en lectura, se pone en cero
        end
//Caso de lectura
        if(T_DATA[29:28]==2'b10)begin
                if(count <= 15 && DATA_RDY!=1)begin //Cuando no se ha recibido recepción completa de palabra serial 
                        nxt_RD_DATA[15:0] = {RD_DATA[14:0],MDIO_IN};
                end

                if (count==0)begin
                        nxt_DATA_RDY = 1;
                end
        end
        if(count==0)begin
                nxt_MDIO_OE = 0; //Luego de los 32bits de lectura se pone en cero
        end
        end
end
endmodule

Verilog/MDIO_transaction_generator/DUT.v
`include "generadortrans_MDIO.v"

module DUT(CLK, MDC, RESET, MDIO_START, MDIO_OUT, MDIO_OE, MDIO_IN, T_DATA, RD_DATA, DATA_RDY);

//Entradas

input wire CLK, RESET, MDIO_START, MDIO_IN;
input wire [31:0] T_DATA;

//Salidas
output wire [15:0] RD_DATA;
output wire DATA_RDY, MDC, MDIO_OE, MDIO_OUT;

mdio inst1(

.CLK            (CLK),
.MDC            (MDC),
.RESET          (RESET),
.MDIO_START     (MDIO_START),
.MDIO_OUT       (MDIO_OUT),
.MDIO_OE        (MDIO_OE),
.MDIO_IN        (MDIO_IN),
.T_DATA         (T_DATA),
.RD_DATA        (RD_DATA),
.DATA_RDY       (DATA_RDY)
);

endmodule

Verilog/MDIO_transaction_generator/testescritura.v
module testerescritura(CLK, MDC, RESET, MDIO_START, MDIO_OUT, MDIO_OE, MDIO_IN, T_DATA, RD_DATA, DATA_RDY);

//Entradas
output reg CLK, RESET, MDIO_START, MDIO_IN;
output reg [31:0] T_DATA;

//Salida
input wire [15:0] RD_DATA;
input wire DATA_RDY, MDC, MDIO_OE, MDIO_OUT;

//Reloj
        always #2 CLK = ~CLK;
//Valores de testbench
integer i=0, seed;

initial begin
        $dumpfile("testMDIO.vcd");
        $dumpvars();
//Valores iniciales
        CLK <= 1;
        RESET <= 0;
        #5
        RESET <= 1;
        MDIO_START <= 1;
        T_DATA <= 32'h0x51115F1F; //Valor de prueba que indica lectura
        for (i=0;i<70;i=i+1)begin
                #3 seed = $urandom%2;
                MDIO_IN = seed;
        end
        #100;
        RESET <= 0;
        #20;

        $finish;
end

endmodule

Verilog/MDIO_transaction_generator/testbench.v
`include "testlectura.v"
`include "testescritura.v"
`include "DUT.v"

//Lectura

module lectura_tb;

//Entradas
wire CLK, RESET, MDIO_START, MDIO_IN;
wire [31:0] T_DATA;

//Salidas
wire [15:0] RD_DATA;
wire DATA_RDY, MDC, MDIO_OE, MDIO_OUT;

DUT MDIO(
.CLK            (CLK),
.MDC            (MDC),
.RESET          (RESET),
.MDIO_START     (MDIO_START),
.MDIO_OUT       (MDIO_OUT),
.MDIO_OE        (MDIO_OE),
.MDIO_IN        (MDIO_IN),
.T_DATA         (T_DATA),
.RD_DATA        (RD_DATA),
.DATA_RDY       (DATA_RDY)
);

testerlectura testlectura(
.CLK            (CLK),
.MDC            (MDC),
.RESET          (RESET),
.MDIO_START     (MDIO_START),
.MDIO_OUT       (MDIO_OUT),
.MDIO_OE        (MDIO_OE),
.MDIO_IN        (MDIO_IN),
.T_DATA         (T_DATA),
.RD_DATA        (RD_DATA),
.DATA_RDY       (DATA_RDY)
);

endmodule

//Escritura

module escritura_tb;

//Entradas
wire CLK, RESET, MDIO_START, MDIO_IN;
wire [31:0] T_DATA;

//Salidas
wire [15:0] RD_DATA;
wire DATA_RDY, MDC, MDIO_OE, MDIO_OUT;

DUT MDIO(
.CLK            (CLK),
.MDC            (MDC),
.RESET          (RESET),
.MDIO_START     (MDIO_START),
.MDIO_OUT       (MDIO_OUT),
.MDIO_OE        (MDIO_OE),
.MDIO_IN        (MDIO_IN),
.T_DATA         (T_DATA),
.RD_DATA        (RD_DATA),
.DATA_RDY       (DATA_RDY)
);

testerescritura testescritura(
.CLK            (CLK),
.MDC            (MDC),
.RESET          (RESET),
.MDIO_START     (MDIO_START),
.MDIO_OUT       (MDIO_OUT),
.MDIO_OE        (MDIO_OE),
.MDIO_IN        (MDIO_IN),
.T_DATA         (T_DATA),
.RD_DATA        (RD_DATA),
.DATA_RDY       (DATA_RDY)
);

endmodule

Verilog/MDIO_transaction_generator/testMDIO.vcd
$date
	Thu Aug 17 15:59:42 2023
$end
$version
	Icarus Verilog
$end
$timescale
	1s
$end
$scope module escritura_tb $end
$var wire 32 ! T_DATA [31:0] $end
$var wire 1 " RESET $end
$var wire 16 # RD_DATA [15:0] $end
$var wire 1 $ MDIO_START $end
$var wire 1 % MDIO_OUT $end
$var wire 1 & MDIO_OE $end
$var wire 1 ' MDIO_IN $end
$var wire 1 ( MDC $end
$var wire 1 ) DATA_RDY $end
$var wire 1 * CLK $end
$scope module MDIO $end
$var wire 32 + T_DATA [31:0] $end
$var wire 1 " RESET $end
$var wire 16 , RD_DATA [15:0] $end
$var wire 1 $ MDIO_START $end
$var wire 1 % MDIO_OUT $end
$var wire 1 & MDIO_OE $end
$var wire 1 ' MDIO_IN $end
$var wire 1 ( MDC $end
$var wire 1 ) DATA_RDY $end
$var wire 1 * CLK $end
$scope module inst1 $end
$var wire 32 - T_DATA [31:0] $end
$var wire 1 " RESET $end
$var wire 1 $ MDIO_START $end
$var wire 1 ' MDIO_IN $end
$var wire 1 * CLK $end
$var reg 1 ) DATA_RDY $end
$var reg 1 ( MDC $end
$var reg 1 & MDIO_OE $end
$var reg 1 % MDIO_OUT $end
$var reg 16 . RD_DATA [15:0] $end
$var reg 6 / count [5:0] $end
$var reg 1 0 nxt_DATA_RDY $end
$var reg 1 1 nxt_MDIO_OE $end
$var reg 1 2 nxt_MDIO_OUT $end
$var reg 16 3 nxt_RD_DATA [15:0] $end
$var reg 6 4 nxt_count [5:0] $end
$upscope $end
$upscope $end
$scope module testescritura $end
$var wire 1 ) DATA_RDY $end
$var wire 1 ( MDC $end
$var wire 1 & MDIO_OE $end
$var wire 1 % MDIO_OUT $end
$var wire 16 5 RD_DATA [15:0] $end
$var reg 1 * CLK $end
$var reg 1 ' MDIO_IN $end
$var reg 1 $ MDIO_START $end
$var reg 1 " RESET $end
$var reg 32 6 T_DATA [31:0] $end
$var integer 32 7 i [31:0] $end
$var integer 32 8 seed [31:0] $end
$upscope $end
$upscope $end
$scope module lectura_tb $end
$var wire 32 9 T_DATA [31:0] $end
$var wire 1 : RESET $end
$var wire 16 ; RD_DATA [15:0] $end
$var wire 1 < MDIO_START $end
$var wire 1 = MDIO_OUT $end
$var wire 1 > MDIO_OE $end
$var wire 1 ? MDIO_IN $end
$var wire 1 @ MDC $end
$var wire 1 A DATA_RDY $end
$var wire 1 B CLK $end
$scope module MDIO $end
$var wire 32 C T_DATA [31:0] $end
$var wire 1 : RESET $end
$var wire 16 D RD_DATA [15:0] $end
$var wire 1 < MDIO_START $end
$var wire 1 = MDIO_OUT $end
$var wire 1 > MDIO_OE $end
$var wire 1 ? MDIO_IN $end
$var wire 1 @ MDC $end
$var wire 1 A DATA_RDY $end
$var wire 1 B CLK $end
$scope module inst1 $end
$var wire 32 E T_DATA [31:0] $end
$var wire 1 : RESET $end
$var wire 1 < MDIO_START $end
$var wire 1 ? MDIO_IN $end
$var wire 1 B CLK $end
$var reg 1 A DATA_RDY $end
$var reg 1 @ MDC $end
$var reg 1 > MDIO_OE $end
$var reg 1 = MDIO_OUT $end
$var reg 16 F RD_DATA [15:0] $end
$var reg 6 G count [5:0] $end
$var reg 1 H nxt_DATA_RDY $end
$var reg 1 I nxt_MDIO_OE $end
$var reg 1 J nxt_MDIO_OUT $end
$var reg 16 K nxt_RD_DATA [15:0] $end
$var reg 6 L nxt_count [5:0] $end
$upscope $end
$upscope $end
$scope module testlectura $end
$var wire 1 A DATA_RDY $end
$var wire 1 @ MDC $end
$var wire 1 > MDIO_OE $end
$var wire 1 = MDIO_OUT $end
$var wire 16 M RD_DATA [15:0] $end
$var reg 1 B CLK $end
$var reg 1 ? MDIO_IN $end
$var reg 1 < MDIO_START $end
$var reg 1 : RESET $end
$var reg 32 N T_DATA [31:0] $end
$var integer 32 O i [31:0] $end
$var integer 32 P seed [31:0] $end
$upscope $end
$upscope $end
$scope module escritura_tb $end
$scope module MDIO $end
$scope module inst1 $end
$upscope $end
$upscope $end
$scope module testescritura $end
$upscope $end
$upscope $end
$scope module lectura_tb $end
$scope module MDIO $end
$scope module inst1 $end
$upscope $end
$upscope $end
$scope module testlectura $end
$upscope $end
$upscope $end
$enddefinitions $end
#0
$dumpvars
bx P
b0 O
bx N
bx M
bx L
bx K
xJ
xI
xH
bx G
bx F
bx E
bx D
bx C
1B
xA
0@
x?
x>
x=
x<
bx ;
0:
bx 9
bx 8
b0 7
bx 6
bx 5
bx 4
bx 3
x2
x1
x0
bx /
bx .
bx -
bx ,
bx +
1*
x)
0(
x'
x&
x%
x$
bx #
0"
bx !
$end
#2
0B
0*
#4
1B
1*
#5
b11110 L
b11110 4
b11111 G
b11111 /
0J
1I
0H
02
11
00
b1100001000100010101111100011111 9
b1100001000100010101111100011111 C
b1100001000100010101111100011111 E
b1100001000100010101111100011111 N
1<
1:
b1010001000100010101111100011111 !
b1010001000100010101111100011111 +
b1010001000100010101111100011111 -
b1010001000100010101111100011111 6
1$
1"
#6
0B
0*
#8
1J
12
0=
1>
0A
b11110 G
0%
1&
0)
b11110 /
1@
1(
1I
b11101 L
11
b11101 4
1B
1*
b1 O
1?
b1 P
b1 7
0'
b0 8
#10
0B
0*
#11
12
11
b11101 4
b10 O
b10 7
1'
b1 8
#12
0@
0(
1B
1*
#14
0B
0*
b11 O
b11 7
#16
b11100 L
1J
1I
b11100 4
02
11
1=
b11101 G
1%
b11101 /
1@
1(
1B
1*
#17
1J
1I
b11100 L
b100 O
0?
b0 P
b100 7
#18
0B
0*
#20
0@
0(
1J
1I
b11100 L
1B
1*
b101 O
1?
b1 P
b101 7
#22
0B
0*
#23
11
b11100 4
b110 O
b110 7
0'
b0 8
#24
b11011 L
0J
1I
b11011 4
12
11
b11100 G
0%
b11100 /
1@
1(
1B
1*
#26
1I
b11011 L
12
11
b11011 4
0B
0*
b111 O
0?
b0 P
b111 7
1'
b1 8
#28
0@
0(
1B
1*
#29
b1000 O
b1000 7
#30
0B
0*
#32
b11010 L
1I
b11010 4
02
11
0=
b11011 G
1%
b11011 /
1@
1(
1B
1*
b1001 O
b1001 7
#34
0B
0*
#35
1I
b11010 L
b1010 O
1?
b1 P
b1010 7
#36
0@
0(
1B
1*
#38
11
b11010 4
0B
0*
b1011 O
b1011 7
0'
b0 8
#40
b11001 L
1I
b11001 4
11
b11010 G
0%
b11010 /
1@
1(
1B
1*
#41
1I
b11001 L
b1100 O
0?
b0 P
b1100 7
#42
0B
0*
#44
0@
0(
1I
b11001 L
1B
1*
b1101 O
1?
b1 P
b1101 7
#46
0B
0*
#47
b1110 O
b1110 7
#48
b11000 L
1I
b11000 4
11
b11001 G
b11001 /
1@
1(
1B
1*
#50
11
b11000 4
0B
0*
b1111 O
b1111 7
1'
b1 8
#52
0@
0(
1B
1*
#53
1I
b11000 L
b10000 O
0?
b0 P
b10000 7
#54
0B
0*
#56
b10111 L
1J
1I
12
b11000 G
b11000 /
1@
1(
11
b10111 4
1B
1*
b10001 O
b10001 7
0'
b0 8
#58
0B
0*
#59
1J
1I
b10111 L
b10010 O
1?
b1 P
b10010 7
#60
0@
0(
1B
1*
#62
0B
0*
b10011 O
b10011 7
#64
b10110 L
0J
1I
b10110 4
02
11
1=
b10111 G
1%
b10111 /
1@
1(
1B
1*
#65
11
b10110 4
b10100 O
b10100 7
1'
b1 8
#66
0B
0*
#68
0@
0(
1B
1*
b10101 O
b10101 7
#70
0B
0*
#71
1I
b10110 L
11
b10110 4
b10110 O
0?
b0 P
b10110 7
0'
b0 8
#72
b10101 L
1I
b10101 4
11
0=
b10110 G
0%
b10110 /
1@
1(
1B
1*
#74
1I
b10101 L
11
b10101 4
0B
0*
b10111 O
1?
b1 P
b10111 7
1'
b1 8
#76
0@
0(
1B
1*
#77
1I
b10101 L
b11000 O
0?
b0 P
b11000 7
#78
0B
0*
#80
b10100 L
1I
b10101 G
b10101 /
1@
1(
11
b10100 4
1B
1*
b11001 O
b11001 7
0'
b0 8
#82
0B
0*
#83
b11010 O
b11010 7
#84
0@
0(
1B
1*
#86
11
b10100 4
0B
0*
b11011 O
b11011 7
1'
b1 8
#88
b10011 L
1J
1I
b10011 4
12
11
b10100 G
b10100 /
1@
1(
1B
1*
#89
1J
1I
b10011 L
12
11
b10011 4
b11100 O
1?
b1 P
b11100 7
0'
b0 8
#90
0B
0*
#92
0@
0(
1J
1I
b10011 L
12
11
b10011 4
1B
1*
b11101 O
0?
b0 P
b11101 7
1'
b1 8
#94
0B
0*
#95
12
11
b10011 4
b11110 O
b11110 7
0'
b0 8
#96
b10010 L
0J
1I
b10010 4
02
11
1=
b10011 G
1%
b10011 /
1@
1(
1B
1*
#98
0B
0*
b11111 O
b11111 7
#100
0@
0(
1B
1*
#101
1I
b10010 L
11
b10010 4
b100000 O
1?
b1 P
b100000 7
1'
b1 8
#102
0B
0*
#104
b10001 L
1I
b10001 4
11
0=
b10010 G
0%
b10010 /
1@
1(
1B
1*
b100001 O
b100001 7
#106
0B
0*
#107
1I
b10001 L
b100010 O
0?
b0 P
b100010 7
#108
0@
0(
1B
1*
#110
1I
b10001 L
11
b10001 4
0B
0*
b100011 O
1?
b1 P
b100011 7
0'
b0 8
#112
b10000 L
1I
b10000 4
11
b10001 G
b10001 /
1@
1(
1B
1*
#113
11
b10000 4
b100100 O
b100100 7
1'
b1 8
#114
0B
0*
#116
0@
0(
1I
b10000 L
11
b10000 4
1B
1*
b100101 O
0?
b0 P
b100101 7
0'
b0 8
#118
0B
0*
#119
1I
b10000 L
11
b10000 4
b100110 O
1?
b1 P
b100110 7
1'
b1 8
#120
b1111 L
1J
1I
b1111 4
12
11
b10000 G
b10000 /
1@
1(
1B
1*
#122
12
11
b1111 4
0B
0*
b100111 O
b100111 7
0'
b0 8
#124
0@
0(
1B
1*
#125
1J
1I
b1111 L
12
11
b1111 4
b101000 O
0?
b0 P
b101000 7
1'
b1 8
#126
0B
0*
#128
bx1 K
b1110 4
02
11
1=
b1111 G
1%
b1111 /
1@
1(
0J
0I
b1110 L
1B
1*
b101001 O
1?
b1 P
b101001 7
#130
0B
0*
#131
bx0 K
b1110 L
b101010 O
0?
b0 P
b101010 7
#132
0@
0(
1B
1*
#134
bx1 K
b1110 L
0B
0*
b101011 O
1?
b1 P
b101011 7
#136
bx11 K
b1101 L
1J
b1101 4
12
11
bx1 ;
bx1 D
bx1 F
bx1 M
0=
0>
b1110 G
0%
b1110 /
1@
1(
1B
1*
#137
bx10 K
1J
b1101 L
12
11
b1101 4
b101100 O
0?
b0 P
b101100 7
0'
b0 8
#138
0B
0*
#140
0@
0(
1B
1*
b101101 O
b101101 7
#142
0B
0*
#143
bx11 K
1J
b1101 L
12
11
b1101 4
b101110 O
1?
b1 P
b101110 7
1'
b1 8
#144
bx111 K
b1100 L
0J
b1100 4
02
11
bx11 ;
bx11 D
bx11 F
bx11 M
1=
b1101 G
1%
b1101 /
1@
1(
1B
1*
#146
bx110 K
b1100 L
11
b1100 4
0B
0*
b101111 O
0?
b0 P
b101111 7
0'
b0 8
#148
0@
0(
1B
1*
#149
bx111 K
b1100 L
11
b1100 4
b110000 O
1?
b1 P
b110000 7
1'
b1 8
#150
0B
0*
#152
bx1111 K
b1011 L
1J
b1011 4
12
11
bx111 ;
bx111 D
bx111 F
bx111 M
0=
b1100 G
0%
b1100 /
1@
1(
1B
1*
b110001 O
b110001 7
#154
0B
0*
#155
bx1110 K
1J
b1011 L
b110010 O
0?
b0 P
b110010 7
#156
0@
0(
1B
1*
#158
bx1111 K
1J
b1011 L
0B
0*
b110011 O
1?
b1 P
b110011 7
#160
bx11111 K
b1010 L
1J
b1010 4
12
11
bx1111 ;
bx1111 D
bx1111 F
bx1111 M
1=
b1011 G
1%
b1011 /
1@
1(
1B
1*
#161
bx11110 K
1J
b1010 L
b110100 O
0?
b0 P
b110100 7
#162
0B
0*
#164
0@
0(
12
11
b1010 4
1B
1*
b110101 O
b110101 7
0'
b0 8
#166
0B
0*
#167
b110110 O
b110110 7
#168
bx111100 K
b1001 L
1J
b1001 4
12
11
bx11110 ;
bx11110 D
bx11110 F
bx11110 M
b1010 G
b1010 /
1@
1(
1B
1*
#170
0B
0*
b110111 O
b110111 7
#172
0@
0(
1B
1*
#173
bx111101 K
1J
b1001 L
12
11
b1001 4
b111000 O
1?
b1 P
b111000 7
1'
b1 8
#174
0B
0*
#176
bx1111011 K
b1000 L
1J
b1000 4
12
11
bx111101 ;
bx111101 D
bx111101 F
bx111101 M
b1001 G
b1001 /
1@
1(
1B
1*
b111001 O
b111001 7
#178
0B
0*
#179
bx1111010 K
1J
b1000 L
b111010 O
0?
b0 P
b111010 7
#180
0@
0(
1B
1*
#182
bx1111011 K
1J
b1000 L
0B
0*
b111011 O
1?
b1 P
b111011 7
#184
bx11110111 K
b111 L
1J
b111 4
12
11
bx1111011 ;
bx1111011 D
bx1111011 F
bx1111011 M
b1000 G
b1000 /
1@
1(
1B
1*
#185
bx11110110 K
1J
b111 L
12
11
b111 4
b111100 O
0?
b0 P
b111100 7
0'
b0 8
#186
0B
0*
#188
0@
0(
bx11110111 K
1J
b111 L
12
11
b111 4
1B
1*
b111101 O
1?
b1 P
b111101 7
1'
b1 8
#190
0B
0*
#191
12
11
b111 4
b111110 O
b111110 7
0'
b0 8
#192
bx111101111 K
b110 L
0J
b110 4
02
11
bx11110111 ;
bx11110111 D
bx11110111 F
bx11110111 M
b111 G
b111 /
1@
1(
1B
1*
#194
11
b110 4
0B
0*
b111111 O
b111111 7
1'
b1 8
#196
0@
0(
1B
1*
#197
bx111101110 K
b110 L
b1000000 O
0?
b0 P
b1000000 7
#198
0B
0*
#200
bx1111011100 K
b101 L
bx111101110 ;
bx111101110 D
bx111101110 F
bx111101110 M
0=
b110 G
0%
b110 /
1@
1(
11
b101 4
1B
1*
b1000001 O
b1000001 7
0'
b0 8
#202
0B
0*
#203
11
b101 4
b1000010 O
b1000010 7
1'
b1 8
#204
0@
0(
1B
1*
#206
11
b101 4
0B
0*
b1000011 O
b1000011 7
0'
b0 8
#208
bx11110111000 K
b100 L
b100 4
11
bx1111011100 ;
bx1111011100 D
bx1111011100 F
bx1111011100 M
b101 G
b101 /
1@
1(
1B
1*
#209
bx11110111001 K
b100 L
11
b100 4
b1000100 O
1?
b1 P
b1000100 7
1'
b1 8
#210
0B
0*
#212
0@
0(
bx11110111000 K
b100 L
11
b100 4
1B
1*
b1000101 O
0?
b0 P
b1000101 7
0'
b0 8
#214
0B
0*
#215
11
b100 4
b1000110 O
b1000110 7
1'
b1 8
#216
bx111101110000 K
b11 L
1J
b11 4
12
11
bx11110111000 ;
bx11110111000 D
bx11110111000 F
bx11110111000 M
b100 G
b100 /
1@
1(
1B
1*
#218
0B
0*
#220
0@
0(
1B
1*
#222
0B
0*
#224
bx1111011100000 K
b10 L
1J
b10 4
12
11
bx111101110000 ;
bx111101110000 D
bx111101110000 F
bx111101110000 M
1=
b11 G
1%
b11 /
1@
1(
1B
1*
#226
0B
0*
#228
0@
0(
1B
1*
#230
0B
0*
#232
bx11110111000000 K
b1 L
1J
b1 4
12
11
bx1111011100000 ;
bx1111011100000 D
bx1111011100000 F
bx1111011100000 M
b10 G
b10 /
1@
1(
1B
1*
#234
0B
0*
#236
0@
0(
1B
1*
#238
0B
0*
#240
bx111101110000000 K
b0 L
1J
b0 4
12
11
bx11110111000000 ;
bx11110111000000 D
bx11110111000000 F
bx11110111000000 M
b1 G
b1 /
1@
1(
1B
1*
#242
0B
0*
#244
0@
0(
1B
1*
#246
0B
0*
#248
1H
b1111011100000000 K
1J
12
01
bx111101110000000 ;
bx111101110000000 D
bx111101110000000 F
bx111101110000000 M
b0 G
b0 /
1@
1(
1B
1*
#250
0B
0*
#252
0@
0(
1B
1*
#254
0B
0*
#256
1J
1H
b1111011100000000 ;
b1111011100000000 D
b1111011100000000 F
b1111011100000000 M
1A
0&
1@
1(
1B
1*
#258
0B
0*
#260
0@
0(
1B
1*
#262
0B
0*
#264
1@
1(
1B
1*
#266
0B
0*
#268
0@
0(
1B
1*
#270
0B
0*
#272
1@
1(
1B
1*
#274
0B
0*
#276
0@
0(
1B
1*
#278
0B
0*
#280
1@
1(
1B
1*
#282
0B
0*
#284
0@
0(
1B
1*
#286
0B
0*
#288
1@
1(
1B
1*
#290
0B
0*
#292
0@
0(
1B
1*
#294
0B
0*
#296
1@
1(
1B
1*
#298
0B
0*
#300
0@
0(
1B
1*
#302
0B
0*
#304
1@
1(
1B
1*
#306
0B
0*
#308
0@
0(
1B
1*
#310
0B
0*
#312
1@
1(
1B
1*
#314
0B
0*
#315
0:
0"
#316
0@
0(
1B
1*
