Verilog/4bits_shiftregister/tester.v
module Probador(S_OUT,clk,ENB,DIR,S_IN,MODO,D,Q);

// Salidas
input wire S_OUT;
input wire  [3:0] Q;

// Entradas
output reg clk, ENB, DIR, S_IN; 
output reg  [3:0] D;
output reg [1:0] MODO;

//Inicio testbench

    initial	clk <= 0;
    always begin
        #1 clk <= !clk;
    end

    initial begin
        // Se genera un display para cuando se corra el vvp 
        $dumpfile("testregistro.vcd");
        $dumpvars(0, testbench);
        $display("\t\t------------------------------------------");
        $display("\t\tTime\| clk \|  DIR  \|  S_IN \|  MODO  \| S_OUT");
        $display("\t\t------------------------------------------");
        $monitor( $time, "|\t%b |\t%b |\t%b |\t%b |\t%b ", clk, DIR, S_IN, MODO, S_OUT);
        
        // Rotación a la izquierda
            clk <= 1;
            ENB=0;
            #2
            ENB=1;
            D[3:0]=4'b0000;
            MODO[1:0]= 2'b10;
            DIR=0;
            S_IN=1;
            #2
            MODO[1:0]= 2'b00;
            #15
        // Reset    
            ENB=0;  
            S_IN=0;            
        // Rotación de a la derecha
            MODO[1:0]= 10;
            #2 
            ENB=1;
            D[3:0]=4'b00x0;            
            DIR=1;
            S_IN=1;
            #2
            MODO[1:0]=00;
            #15
 
        // Rotación circular a la izquierda
            MODO[1:0]= 10;
            #2 
            ENB=1;
            D[3:0]=4'b1010;            
            DIR=0;
            S_IN=1;
            #2
            MODO[1:0]=01;
            #15
        // Reset    
            ENB=0;  
            S_IN=0;   
        // Rotación circular a la derecha
            MODO[1:0]= 10;
            #2 
            ENB=1;
            D[3:0]=4'b0001;            
            DIR=0;
            S_IN=1;
            #2
            MODO[1:0]=01;
            #15  
        // Reset    
            ENB=0;  
            S_IN=0; 
        // Carga paralela
            MODO[1:0]= 10;
            #2 
            ENB=1;
            D[3:0]=4'b1001;            
            DIR=0;
            S_IN=1;
            #15
            $finish;
    end 


endmodule

Verilog/4bits_shiftregister/registrofinal.v
//Código de tarea para registro desplazable de 4 bits
//Daniel Chacón Mora-B72018

module registrodesplazable(S_OUT,clk,ENB,DIR,S_IN,MODO,D,Q);

        input clk;
        input ENB;
        input DIR;
        input S_IN;
        input [1:0] MODO;
        input [3:0] D;
        output reg [3:0] Q;
        output reg S_OUT;

always @ (posedge clk)
begin
	if (ENB==1)begin
		//Rotación hacia la izquierda
		if (DIR==0 && MODO==2'b00)
			begin
			Q <= {Q[2:0],S_IN};
			S_OUT <= Q[0];
			end
		//Rotación hacia la derecha 
		else if (DIR==1 && MODO==2'b00)begin
			Q <= {S_IN,Q[3:1]};
			S_OUT <= Q[3];
			end
		//Rotación circular a la izquierda
		else if (DIR==0 && MODO==2'b01)
			Q[3:0] <= {Q[2:0],Q[3]};
		//Rotación circular a la derecha
		else if (DIR==1 && MODO==2'b01)
			Q[3:0] <= {Q[0],Q[3:1]};
		//Carga en paralelo
		else if ( MODO==2'b10)
			Q[3:0] <= D[3:0];
		else 
		Q[3:0]<=Q[3:0];
		end
	else 
		Q[3:0]<=Q[3:0];
end
endmodule

Verilog/4bits_shiftregister/DUT.v
`include "registrofinal.v"
module DUT(S_OUT, clk, ENB, DIR, S_IN, MODO, D, Q);
	
// Input/Output definition
input wire clk;
input wire ENB;
input wire DIR;
input wire S_IN;
input wire [1:0] MODO;
input wire [3:0] D;
output wire [3:0] Q;
output wire S_OUT;

registrodesplazable inst1(
    .S_OUT  (S_OUT),
    .clk    (clk),
    .ENB    (ENB),
    .DIR    (DIR),
    .S_IN   (S_IN),
    .MODO   (MODO),
    .D      (D),
    .Q      (Q)
);

endmodule

Verilog/4bits_shiftregister/testbench.v
//`include "registrofinal.v"
`include "tester.v"
`include "DUT.v"
// Se define un modulo para el banco de pruebas

module testbench;

// Las senales se definen como cables
wire clk, ENB, DIR, S_IN;
wire S_OUT;
wire  [3:0] Q;
wire  [3:0] D; 
wire [1:0] MODO;

// Se crea instancia del probador

DUT Shiftregister(
    .S_OUT  (S_OUT),
    .clk    (clk),
    .ENB    (ENB),
    .DIR    (DIR),
    .S_IN   (S_IN),
    .MODO   (MODO),
    .D      (D),
    .Q      (Q)
);

Probador Tester(
    .S_OUT  (S_OUT),
    .clk    (clk),
    .ENB    (ENB),
    .DIR    (DIR),
    .S_IN   (S_IN),
    .MODO   (MODO),
    .D      (D),
    .Q      (Q)
);


endmodule

Verilog/4bits_shiftregister/testregistro.vcd
$date
	Thu Aug 17 15:53:10 2023
$end
$version
	Icarus Verilog
$end
$timescale
	1s
$end
$scope module testbench $end
$var wire 1 ! clk $end
$var wire 1 " S_OUT $end
$var wire 1 # S_IN $end
$var wire 4 $ Q [3:0] $end
$var wire 2 % MODO [1:0] $end
$var wire 1 & ENB $end
$var wire 1 ' DIR $end
$var wire 4 ( D [3:0] $end
$scope module Shiftregister $end
$var wire 1 ! clk $end
$var wire 1 " S_OUT $end
$var wire 1 # S_IN $end
$var wire 4 ) Q [3:0] $end
$var wire 2 * MODO [1:0] $end
$var wire 1 & ENB $end
$var wire 1 ' DIR $end
$var wire 4 + D [3:0] $end
$scope module inst1 $end
$var wire 1 ! clk $end
$var wire 1 # S_IN $end
$var wire 2 , MODO [1:0] $end
$var wire 1 & ENB $end
$var wire 1 ' DIR $end
$var wire 4 - D [3:0] $end
$var reg 4 . Q [3:0] $end
$var reg 1 " S_OUT $end
$upscope $end
$upscope $end
$scope module Tester $end
$var wire 4 / Q [3:0] $end
$var wire 1 " S_OUT $end
$var reg 4 0 D [3:0] $end
$var reg 1 ' DIR $end
$var reg 1 & ENB $end
$var reg 2 1 MODO [1:0] $end
$var reg 1 # S_IN $end
$var reg 1 ! clk $end
$upscope $end
$upscope $end
$enddefinitions $end
#0
$dumpvars
bx 1
bx 0
bx /
bx .
bx -
bx ,
bx +
bx *
bx )
bx (
x'
0&
bx %
bx $
x#
x"
1!
$end
#1
0!
#2
0"
b0 $
b0 )
b0 .
b0 /
1!
1#
0'
b10 %
b10 *
b10 ,
b10 1
b0 (
b0 +
b0 -
b0 0
1&
#3
0!
#4
b1 $
b1 )
b1 .
b1 /
1!
b0 %
b0 *
b0 ,
b0 1
#5
0!
#6
b11 $
b11 )
b11 .
b11 /
1!
#7
0!
#8
b111 $
b111 )
b111 .
b111 /
1!
#9
0!
#10
b1111 $
b1111 )
b1111 .
b1111 /
1!
#11
0!
#12
1"
b1111 $
b1111 )
b1111 .
b1111 /
1!
#13
0!
#14
1"
b1111 $
b1111 )
b1111 .
b1111 /
1!
#15
0!
#16
1"
b1111 $
b1111 )
b1111 .
b1111 /
1!
#17
0!
#18
1"
b1111 $
b1111 )
b1111 .
b1111 /
1!
#19
0!
b10 %
b10 *
b10 ,
b10 1
0#
0&
#20
b0 $
b0 )
b0 .
b0 /
1!
#21
0!
1#
1'
b0x0 (
b0x0 +
b0x0 -
b0x0 0
1&
#22
b0x0 $
b0x0 )
b0x0 .
b0x0 /
1!
#23
0!
b0 %
b0 *
b0 ,
b0 1
#24
0"
b100x $
b100x )
b100x .
b100x /
1!
#25
0!
#26
x"
b1100 $
b1100 )
b1100 .
b1100 /
1!
#27
0!
#28
0"
b1110 $
b1110 )
b1110 .
b1110 /
1!
#29
0!
#30
b1111 $
b1111 )
b1111 .
b1111 /
1!
#31
0!
#32
1"
1!
#33
0!
#34
1!
#35
0!
#36
1!
#37
0!
#38
b0x0 $
b0x0 )
b0x0 .
b0x0 /
1!
b10 %
b10 *
b10 ,
b10 1
#39
0!
#40
0"
b1010 $
b1010 )
b1010 .
b1010 /
1!
0'
b1010 (
b1010 +
b1010 -
b1010 0
#41
0!
#42
1"
b101 $
b101 )
b101 .
b101 /
1!
b1 %
b1 *
b1 ,
b1 1
#43
0!
#44
0"
b1010 $
b1010 )
b1010 .
b1010 /
1!
#45
0!
#46
1"
b101 $
b101 )
b101 .
b101 /
1!
#47
0!
#48
0"
b1010 $
b1010 )
b1010 .
b1010 /
1!
#49
0!
#50
1"
b101 $
b101 )
b101 .
b101 /
1!
#51
0!
#52
0"
b1010 $
b1010 )
b1010 .
b1010 /
1!
#53
0!
#54
1"
b101 $
b101 )
b101 .
b101 /
1!
#55
0!
#56
0"
b1010 $
b1010 )
b1010 .
b1010 /
1!
#57
0!
b10 %
b10 *
b10 ,
b10 1
0#
0&
#58
1!
#59
0!
1#
b1 (
b1 +
b1 -
b1 0
1&
#60
b1 $
b1 )
b1 .
b1 /
1!
#61
0!
b1 %
b1 *
b1 ,
b1 1
#62
b10 $
b10 )
b10 .
b10 /
1!
#63
0!
#64
b100 $
b100 )
b100 .
b100 /
1!
#65
0!
#66
b1000 $
b1000 )
b1000 .
b1000 /
1!
#67
0!
#68
1"
b1 $
b1 )
b1 .
b1 /
1!
#69
0!
#70
b10 $
b10 )
b10 .
b10 /
0"
1!
#71
0!
#72
b100 $
b100 )
b100 .
b100 /
1!
#73
0!
#74
b1000 $
b1000 )
b1000 .
b1000 /
1!
#75
0!
#76
b1 $
b1 )
b1 .
b1 /
1!
b10 %
b10 *
b10 ,
b10 1
0#
0&
#77
0!
#78
b1001 $
b1001 )
b1001 .
b1001 /
1!
1#
b1001 (
b1001 +
b1001 -
b1001 0
1&
