Verilog/UART_Transfer/FIFO.v
// Non-ANSI Style JUST IN CASE
//module FIFO (data_in, clk, rst_n, wr_en, rd_en, data_out, wr_ack, overflow, underflow, full, empty, almostfull, almostempty);

    // Parameter declarations
//    parameter FIFO_WIDTH = 8;
//    parameter FIFO_DEPTH = 8;

    // Input port declarations
//    input [FIFO_WIDTH-1:0] data_in;
//    input clk, rst_n, wr_en, rd_en;

    // Output port declarations
//    output [FIFO_WIDTH-1:0] data_out;
//    output wr_ack, overflow, underflow;
//    output full, empty, almostfull, almostempty;

    // Register declarations for outputs
//    reg [FIFO_WIDTH-1:0] data_out;
//    reg wr_ack, overflow, underflow;

    // FIFO logic goes here

//endmodule


module FIFO #(
    parameter FIFO_WIDTH = 8,
    parameter FIFO_DEPTH = 8
)(
    // [N-1:0] range of bits. Verilog uses zero-based indexing
    input [FIFO_WIDTH-1:0] data_in,
    input clk, rst_n, wr_en, rd_en,
    output reg [FIFO_WIDTH-1:0] data_out,
    output reg wr_ack, overflow, underflow,
    output full, empty, almostfull, almostempty
);

// Minimun number of bits required to represent the input number in binary
localparam  max_fifo_addr = $clog2(FIFO_DEPTH-1:0);

// MEM array with FIFO_DEPTH and FIFO_WIDTH on each entry of memory
reg [FIFO_WIDTH-1:0] mem [FIFO_DEPTH-1:0];

// Pointers to track the read and write locations
reg [max_fifo_addr-1:0] wr_ptr, rd_ptr;
reg [max_fifo_addr:0] count; 

always @(posedge clk or posedge rst_n) begin
    // reset
    if (!rst_n) begin
        wr_ptr <= 0;
        wr_ack <=0;
        overflow <= 0;
    end
    else if (wr_en && count < FIFO_DEPTH) begin
        // Data written where pointer indicates
        mem[wr_ptr] <= data_in;
        wr_ack <= 1;
        // Pointer incremented
        wr_ptr <= wr_ptr + 1;
    end
    else if ({wr_en,rd_en} == 2'b00) begin 
    // IDLE state
    end
    // DEFAULT STATE (No write or overwrite)
    else begin
        wr_ack <= 0;
        // FIFO Full and not for reading
        if (full && wr_en && !rd_en) begin
            // Overflow
            overflow <= 1;
        end
        else begin
            overflow <= 0;
        end
    end
// End Always Blocking Posedge
end

always @(posedge clk or negedge rst_n) begin
    // reset
    if (!rst_n) begin 
        rd_prt <= 0;
        underflow <= 0;
    end
    else if (rd_en && count != 0) begin
        // Data read where pointer indicates
        data_out <= mem[rd_ptr];
        // Pointer incremented
        rd_ptr <= rd_ptr + 1;
    end
    else if ({wr_en, rd_en} == 2'b00) begin
        // IDLE STATE
    end
    // Default STATE (no read or overwrite)
    else begin

        if (rd_en && !wr_en && empty) begin
            underflow <= 1;
        end
        else begin
            underflow <= 0;
        end
    end
end

always @(posedge clk or negedge rst_n) begin
    if (!rst_n) begin
        count <= 0;
    end
    else begin
        // Write operation
        if (({wr_en, rd_en} == 2'b10) && !full)
            count <= count + 1;
        // Read operation
        else if (({wr_en, rd_en} == 2'b01) && !empty)
            count <= count - 1;
        else if (({wr_en, rd_en} == 2'b11) && !full) begin
            count <= count - 1;
        end
        else if (({wr_en, rd_en} == 2'b11) && !empty) begin
            count <= count - 1;
        end
        else begin
            // IDLE State
        end            
    end
end

// Combinational logic 
assign full = (count == FIFO_DEPTH)? 1: 0;
assing empty = (count == 0)? 1 : 0;
assign almostfull = (count == FIFO_DEPTH-1)? 1 : 0;
assign almostempty = (count == 1)? 1 : 0;

// Endmodule
endmodule

Verilog/UART_Transfer/RX.v
module rx(
    input s_tick, clk, reset, rx, 
    output reg [7:0] dout,
    output reg rx_done_tick
);

// Params for FSM 
localparam IDLE = 2'b00;
localparam START = 2'b01;
localparam DATA = 2'b10;
localparam STOP = 2'b11;
localparam MIDBIT = 8; // Middle of the bit for oversampling 

reg [1:0] state;
reg [7:0] data_reg;
reg [3:0] count; // Counts up to 15 for 16x oversampling
reg [2:0] bit_count;

// Always block
always @(posedge clk or posedge reset) begin
    // Reset state
    if (reset) begin
        state <= IDLE;
        count <= 0;
        bit_count <= 0;
        rx_done_tick <= 0;
        dout <= 8'b0;
        data_reg <= 8'b0;
    end else begin 
        rx_done_tick <= 0; // Default to 0, pulse only when done
        if (s_tick) begin 
            case(state)

                IDLE: begin
                    if (!rx) begin
                        state <= START;
                        count <= 0;
                        bit_count <= 0;
                    end
                end

                START: begin 
                    if (count == MIDBIT - 1) begin 
                        if  (!rx) begin
                            state <= DATA; 
                            count <= 0;
                        end else begin
                            state <= IDLE;
                        end
                    end else begin 
                        count <= count + 1;
                    end
                end


                DATA: begin 
                    if (count == 15) begin  // Wait 16 ticks per bit
                        data_reg[bit_count] <= rx;  // Capture bit (LSB first)
                        count <= 0;
                        if (bit_count == 7) begin
                            state <= STOP;
                        end else begin
                            bit_count <= bit_count + 1;
                        end

                    end else begin
                        count <= count + 1;
                    end
                end

                STOP: begin
                    if (count == 15) begin  // Wait for stop bit duration
                        state <= IDLE;
                        dout <= data_reg;
                        rx_done_tick <= 1; // Pulse done signal
                    end else begin 
                        count <= count + 1;
                    end
                end
            
            //End cases
            endcase
        end
    // End FSM
    end
// Always block end
end 

endmodule

Verilog/UART_Transfer/baud_rate_generator.v
// ANSI-C Style Module Definition Verilog 2001+

module baud_rate_generator(
    input clk,
    input reset,
    input [31:0] dvsr,
    output reg tick 
);

// NOn ANSI-C Style Module Definition Verilog 1995
//module baud_rate_generator(clk,reset,dvsr,tick);
//    input clk,
//    input reset,
//    input [31:0] dvsr,
//    output reg tick 

// Internal register
reg [31:0] count;

// Always block: triggered on the rising edge of the clk or reset
always @(posedge clk or posedge reset) begin

    // Reset
    if (reset) begin
        count <= 0;
        tick <= 0;
    end

    
    else begin 
        if (count == dvsr) begin
            count <= 0;
            // Pulse transition: 0 to 1 
            tick <= ~tick;
        end
        else begin
            count <= count +1;
        end

    end
end
endmodule

Verilog/UART_Transfer/RX_Tb.v
`include "FIFO.v"
`include "RX.v"
`include "baud_rate_generator.v"

module rx_tb;
    reg clk;
    reg reset;
    reg [31:0] dvsr;
    wire tick;
    reg rx;
    wire [7:0] dout;
    wire rx_done_tick;
    logic rd_uart;
    wire [7:0] r_data;

    // Baud rate generator
    baud_rate_generator baud_gen(
        .clk(clk),
        .reset(reset),
        .dvsr(dvsr),
        .tick(tick)
    );
    // UART RX
    rx u_rx(
        .s_tick(tick),
        .clk(clk),
        .reset(reset),
        .rx(rx),
        .dout(dout),
        .rx_done_tick(rx_done_tick)
    );
    // FIFO 
    FIFO fifo(
        .data_in(dout),
        .wr_en(rx_done_tick),
        .rd_en(rd_uart),
        .clk(clk),
        .rst_n(~reset),
        .full(full),
        .empty(empty),
        .data_out(r_data)
    );

    initial begin
        clk = 0;
        forever #5 clk = ~clk;
    end

    // Apply reset
    initial begin
        reset = 1;
        #20 reset = 0;
    end

    initial begin
        dvsr = 0;
        rx = 1;
        rd_uart = 0;

        // Dump waveform data
        $dumpfile("test_RX_UART.vcd");
        // Dump all signs from testbench
        $dumpvars(0, rx_tb);
        // Wait reset to complete
        #30;

        // Send start bit (0)
        rx = 0;
        #320; // WAit for 1 bit duration 16*540ns

        // Send data bits (LSB first: 1,0,1,0,0,1,0,1)
        rx = 1; // bit 0
        #320;
        rx = 0; // bit 1
        #320;
        rx = 1; // bit 2
        #320;
        rx = 0; // bit 3
        #320;
        rx = 0; // bit 4
        #320;
        rx = 1; // bit 5
        #320;
        rx = 0; // bit 6
        #320;
        rx = 1; // bit 7
        #320;

        // send stop bit (1)
        rx = 1;
        #320;

        rd_uart = 1;
        #320;
        $display("Received data: 0x%h", r_data);
        if (dout == 8'hA5)
            $display("Test Passed!");
        else 
            $display("Test failed!");
        $finish;
    end
endmodule

Verilog/UART_Transfer/test_RX_UART.vcd
$date
	Fri Mar 14 21:08:07 2025
$end
$version
	Icarus Verilog
$end
$timescale
	1s
$end
$scope module rx_tb $end
$var wire 1 ! tick $end
$var wire 1 " rx_done_tick $end
$var wire 8 # r_data [7:0] $end
$var wire 1 $ full $end
$var wire 1 % empty $end
$var wire 8 & dout [7:0] $end
$var reg 1 ' clk $end
$var reg 32 ( dvsr [31:0] $end
$var reg 1 ) rd_uart $end
$var reg 1 * reset $end
$var reg 1 + rx $end
$scope module baud_gen $end
$var wire 1 ' clk $end
$var wire 32 , dvsr [31:0] $end
$var wire 1 * reset $end
$var reg 32 - count [31:0] $end
$var reg 1 ! tick $end
$upscope $end
$scope module fifo $end
$var wire 1 ' clk $end
$var wire 1 ) rd_en $end
$var wire 1 . rst_n $end
$var wire 1 " wr_en $end
$var wire 1 $ full $end
$var wire 1 % empty $end
$var wire 8 / data_in [7:0] $end
$var wire 1 0 almostfull $end
$var wire 1 1 almostempty $end
$var reg 4 2 count [3:0] $end
$var reg 8 3 data_out [7:0] $end
$var reg 1 4 overflow $end
$var reg 3 5 rd_ptr [2:0] $end
$var reg 1 6 underflow $end
$var reg 1 7 wr_ack $end
$var reg 3 8 wr_ptr [2:0] $end
$upscope $end
$scope module u_rx $end
$var wire 1 ' clk $end
$var wire 1 * reset $end
$var wire 1 + rx $end
$var wire 1 ! s_tick $end
$var reg 3 9 bit_count [2:0] $end
$var reg 4 : count [3:0] $end
$var reg 8 ; data_reg [7:0] $end
$var reg 8 < dout [7:0] $end
$var reg 1 " rx_done_tick $end
$var reg 2 = state [1:0] $end
$upscope $end
$upscope $end
$enddefinitions $end
#0
$dumpvars
b0 =
b0 <
b0 ;
b0 :
b0 9
bx 8
x7
06
b0 5
x4
bx 3
b0 2
01
00
b0 /
0.
b0 -
b0 ,
1+
1*
0)
b0 (
0'
b0 &
1%
0$
bx #
0"
0!
$end
#5
04
07
b0 8
1'
#10
0'
#15
1'
#20
1.
0'
0*
#25
1!
1'
#30
0'
0+
#35
0!
b1 =
1'
#40
0'
#45
1!
1'
#50
0'
#55
0!
b1 :
1'
#60
0'
#65
1!
1'
#70
0'
#75
0!
b10 :
1'
#80
0'
#85
1!
1'
#90
0'
#95
0!
b11 :
1'
#100
0'
#105
1!
1'
#110
0'
#115
0!
b100 :
1'
#120
0'
#125
1!
1'
#130
0'
#135
0!
b101 :
1'
#140
0'
#145
1!
1'
#150
0'
#155
0!
b110 :
1'
#160
0'
#165
1!
1'
#170
0'
#175
0!
b111 :
1'
#180
0'
#185
1!
1'
#190
0'
#195
0!
b0 :
b10 =
1'
#200
0'
#205
1!
1'
#210
0'
#215
0!
b1 :
1'
#220
0'
#225
1!
1'
#230
0'
#235
0!
b10 :
1'
#240
0'
#245
1!
1'
#250
0'
#255
0!
b11 :
1'
#260
0'
#265
1!
1'
#270
0'
#275
0!
b100 :
1'
#280
0'
#285
1!
1'
#290
0'
#295
0!
b101 :
1'
#300
0'
#305
1!
1'
#310
0'
#315
0!
b110 :
1'
#320
0'
#325
1!
1'
#330
0'
#335
0!
b111 :
1'
#340
0'
#345
1!
1'
#350
0'
1+
#355
0!
b1000 :
1'
#360
0'
#365
1!
1'
#370
0'
#375
0!
b1001 :
1'
#380
0'
#385
1!
1'
#390
0'
#395
0!
b1010 :
1'
#400
0'
#405
1!
1'
#410
0'
#415
0!
b1011 :
1'
#420
0'
#425
1!
1'
#430
0'
#435
0!
b1100 :
1'
#440
0'
#445
1!
1'
#450
0'
#455
0!
b1101 :
1'
#460
0'
#465
1!
1'
#470
0'
#475
0!
b1110 :
1'
#480
0'
#485
1!
1'
#490
0'
#495
0!
b1111 :
1'
#500
0'
#505
1!
1'
#510
0'
#515
0!
b1 9
b0 :
b1 ;
1'
#520
0'
#525
1!
1'
#530
0'
#535
0!
b1 :
1'
#540
0'
#545
1!
1'
#550
0'
#555
0!
b10 :
1'
#560
0'
#565
1!
1'
#570
0'
#575
0!
b11 :
1'
#580
0'
#585
1!
1'
#590
0'
#595
0!
b100 :
1'
#600
0'
#605
1!
1'
#610
0'
#615
0!
b101 :
1'
#620
0'
#625
1!
1'
#630
0'
#635
0!
b110 :
1'
#640
0'
#645
1!
1'
#650
0'
#655
0!
b111 :
1'
#660
0'
#665
1!
1'
#670
0'
0+
#675
0!
b1000 :
1'
#680
0'
#685
1!
1'
#690
0'
#695
0!
b1001 :
1'
#700
0'
#705
1!
1'
#710
0'
#715
0!
b1010 :
1'
#720
0'
#725
1!
1'
#730
0'
#735
0!
b1011 :
1'
#740
0'
#745
1!
1'
#750
0'
#755
0!
b1100 :
1'
#760
0'
#765
1!
1'
#770
0'
#775
0!
b1101 :
1'
#780
0'
#785
1!
1'
#790
0'
#795
0!
b1110 :
1'
#800
0'
#805
1!
1'
#810
0'
#815
0!
b1111 :
1'
#820
0'
#825
1!
1'
#830
0'
#835
0!
b10 9
b0 :
1'
#840
0'
#845
1!
1'
#850
0'
#855
0!
b1 :
1'
#860
0'
#865
1!
1'
#870
0'
#875
0!
b10 :
1'
#880
0'
#885
1!
1'
#890
0'
#895
0!
b11 :
1'
#900
0'
#905
1!
1'
#910
0'
#915
0!
b100 :
1'
#920
0'
#925
1!
1'
#930
0'
#935
0!
b101 :
1'
#940
0'
#945
1!
1'
#950
0'
#955
0!
b110 :
1'
#960
0'
#965
1!
1'
#970
0'
#975
0!
b111 :
1'
#980
0'
#985
1!
1'
#990
0'
1+
#995
0!
b1000 :
1'
#1000
0'
#1005
1!
1'
#1010
0'
#1015
0!
b1001 :
1'
#1020
0'
#1025
1!
1'
#1030
0'
#1035
0!
b1010 :
1'
#1040
0'
#1045
1!
1'
#1050
0'
#1055
0!
b1011 :
1'
#1060
0'
#1065
1!
1'
#1070
0'
#1075
0!
b1100 :
1'
#1080
0'
#1085
1!
1'
#1090
0'
#1095
0!
b1101 :
1'
#1100
0'
#1105
1!
1'
#1110
0'
#1115
0!
b1110 :
1'
#1120
0'
#1125
1!
1'
#1130
0'
#1135
0!
b1111 :
1'
#1140
0'
#1145
1!
1'
#1150
0'
#1155
0!
b11 9
b0 :
b101 ;
1'
#1160
0'
#1165
1!
1'
#1170
0'
#1175
0!
b1 :
1'
#1180
0'
#1185
1!
1'
#1190
0'
#1195
0!
b10 :
1'
#1200
0'
#1205
1!
1'
#1210
0'
#1215
0!
b11 :
1'
#1220
0'
#1225
1!
1'
#1230
0'
#1235
0!
b100 :
1'
#1240
0'
#1245
1!
1'
#1250
0'
#1255
0!
b101 :
1'
#1260
0'
#1265
1!
1'
#1270
0'
#1275
0!
b110 :
1'
#1280
0'
#1285
1!
1'
#1290
0'
#1295
0!
b111 :
1'
#1300
0'
#1305
1!
1'
#1310
0'
0+
#1315
0!
b1000 :
1'
#1320
0'
#1325
1!
1'
#1330
0'
#1335
0!
b1001 :
1'
#1340
0'
#1345
1!
1'
#1350
0'
#1355
0!
b1010 :
1'
#1360
0'
#1365
1!
1'
#1370
0'
#1375
0!
b1011 :
1'
#1380
0'
#1385
1!
1'
#1390
0'
#1395
0!
b1100 :
1'
#1400
0'
#1405
1!
1'
#1410
0'
#1415
0!
b1101 :
1'
#1420
0'
#1425
1!
1'
#1430
0'
#1435
0!
b1110 :
1'
#1440
0'
#1445
1!
1'
#1450
0'
#1455
0!
b1111 :
1'
#1460
0'
#1465
1!
1'
#1470
0'
#1475
0!
b100 9
b0 :
1'
#1480
0'
#1485
1!
1'
#1490
0'
#1495
0!
b1 :
1'
#1500
0'
#1505
1!
1'
#1510
0'
#1515
0!
b10 :
1'
#1520
0'
#1525
1!
1'
#1530
0'
#1535
0!
b11 :
1'
#1540
0'
#1545
1!
1'
#1550
0'
#1555
0!
b100 :
1'
#1560
0'
#1565
1!
1'
#1570
0'
#1575
0!
b101 :
1'
#1580
0'
#1585
1!
1'
#1590
0'
#1595
0!
b110 :
1'
#1600
0'
#1605
1!
1'
#1610
0'
#1615
0!
b111 :
1'
#1620
0'
#1625
1!
1'
#1630
0'
#1635
0!
b1000 :
1'
#1640
0'
#1645
1!
1'
#1650
0'
#1655
0!
b1001 :
1'
#1660
0'
#1665
1!
1'
#1670
0'
#1675
0!
b1010 :
1'
#1680
0'
#1685
1!
1'
#1690
0'
#1695
0!
b1011 :
1'
#1700
0'
#1705
1!
1'
#1710
0'
#1715
0!
b1100 :
1'
#1720
0'
#1725
1!
1'
#1730
0'
#1735
0!
b1101 :
1'
#1740
0'
#1745
1!
1'
#1750
0'
#1755
0!
b1110 :
1'
#1760
0'
#1765
1!
1'
#1770
0'
#1775
0!
b1111 :
1'
#1780
0'
#1785
1!
1'
#1790
0'
#1795
0!
b101 9
b0 :
1'
#1800
0'
#1805
1!
1'
#1810
0'
#1815
0!
b1 :
1'
#1820
0'
#1825
1!
1'
#1830
0'
#1835
0!
b10 :
1'
#1840
0'
#1845
1!
1'
#1850
0'
#1855
0!
b11 :
1'
#1860
0'
#1865
1!
1'
#1870
0'
#1875
0!
b100 :
1'
#1880
0'
#1885
1!
1'
#1890
0'
#1895
0!
b101 :
1'
#1900
0'
#1905
1!
1'
#1910
0'
#1915
0!
b110 :
1'
#1920
0'
#1925
1!
1'
#1930
0'
#1935
0!
b111 :
1'
#1940
0'
#1945
1!
1'
#1950
0'
1+
#1955
0!
b1000 :
1'
#1960
0'
#1965
1!
1'
#1970
0'
#1975
0!
b1001 :
1'
#1980
0'
#1985
1!
1'
#1990
0'
#1995
0!
b1010 :
1'
#2000
0'
#2005
1!
1'
#2010
0'
#2015
0!
b1011 :
1'
#2020
0'
#2025
1!
1'
#2030
0'
#2035
0!
b1100 :
1'
#2040
0'
#2045
1!
1'
#2050
0'
#2055
0!
b1101 :
1'
#2060
0'
#2065
1!
1'
#2070
0'
#2075
0!
b1110 :
1'
#2080
0'
#2085
1!
1'
#2090
0'
#2095
0!
b1111 :
1'
#2100
0'
#2105
1!
1'
#2110
0'
#2115
0!
b110 9
b0 :
b100101 ;
1'
#2120
0'
#2125
1!
1'
#2130
0'
#2135
0!
b1 :
1'
#2140
0'
#2145
1!
1'
#2150
0'
#2155
0!
b10 :
1'
#2160
0'
#2165
1!
1'
#2170
0'
#2175
0!
b11 :
1'
#2180
0'
#2185
1!
1'
#2190
0'
#2195
0!
b100 :
1'
#2200
0'
#2205
1!
1'
#2210
0'
#2215
0!
b101 :
1'
#2220
0'
#2225
1!
1'
#2230
0'
#2235
0!
b110 :
1'
#2240
0'
#2245
1!
1'
#2250
0'
#2255
0!
b111 :
1'
#2260
0'
#2265
1!
1'
#2270
0'
0+
#2275
0!
b1000 :
1'
#2280
0'
#2285
1!
1'
#2290
0'
#2295
0!
b1001 :
1'
#2300
0'
#2305
1!
1'
#2310
0'
#2315
0!
b1010 :
1'
#2320
0'
#2325
1!
1'
#2330
0'
#2335
0!
b1011 :
1'
#2340
0'
#2345
1!
1'
#2350
0'
#2355
0!
b1100 :
1'
#2360
0'
#2365
1!
1'
#2370
0'
#2375
0!
b1101 :
1'
#2380
0'
#2385
1!
1'
#2390
0'
#2395
0!
b1110 :
1'
#2400
0'
#2405
1!
1'
#2410
0'
#2415
0!
b1111 :
1'
#2420
0'
#2425
1!
1'
#2430
0'
#2435
0!
b111 9
b0 :
1'
#2440
0'
#2445
1!
1'
#2450
0'
#2455
0!
b1 :
1'
#2460
0'
#2465
1!
1'
#2470
0'
#2475
0!
b10 :
1'
#2480
0'
#2485
1!
1'
#2490
0'
#2495
0!
b11 :
1'
#2500
0'
#2505
1!
1'
#2510
0'
#2515
0!
b100 :
1'
#2520
0'
#2525
1!
1'
#2530
0'
#2535
0!
b101 :
1'
#2540
0'
#2545
1!
1'
#2550
0'
#2555
0!
b110 :
1'
#2560
0'
#2565
1!
1'
#2570
0'
#2575
0!
b111 :
1'
#2580
0'
#2585
1!
1'
#2590
0'
1+
#2595
0!
b1000 :
1'
#2600
0'
#2605
1!
1'
#2610
0'
#2615
0!
b1001 :
1'
#2620
0'
#2625
1!
1'
#2630
0'
#2635
0!
b1010 :
1'
#2640
0'
#2645
1!
1'
#2650
0'
#2655
0!
b1011 :
1'
#2660
0'
#2665
1!
1'
#2670
0'
#2675
0!
b1100 :
1'
#2680
0'
#2685
1!
1'
#2690
0'
#2695
0!
b1101 :
1'
#2700
0'
#2705
1!
1'
#2710
0'
#2715
0!
b1110 :
1'
#2720
0'
#2725
1!
1'
#2730
0'
#2735
0!
b1111 :
1'
#2740
0'
#2745
1!
1'
#2750
0'
#2755
0!
b11 =
b0 :
b10100101 ;
1'
#2760
0'
#2765
1!
1'
#2770
0'
#2775
0!
b1 :
1'
#2780
0'
#2785
1!
1'
#2790
0'
#2795
0!
b10 :
1'
#2800
0'
#2805
1!
1'
#2810
0'
#2815
0!
b11 :
1'
#2820
0'
#2825
1!
1'
#2830
0'
#2835
0!
b100 :
1'
#2840
0'
#2845
1!
1'
#2850
0'
#2855
0!
b101 :
1'
#2860
0'
#2865
1!
1'
#2870
0'
#2875
0!
b110 :
1'
#2880
0'
#2885
1!
1'
#2890
0'
#2895
0!
b111 :
1'
#2900
0'
#2905
1!
1'
#2910
0'
#2915
0!
b1000 :
1'
#2920
0'
#2925
1!
1'
#2930
0'
#2935
0!
b1001 :
1'
#2940
0'
#2945
1!
1'
#2950
0'
#2955
0!
b1010 :
1'
#2960
0'
#2965
1!
1'
#2970
0'
#2975
0!
b1011 :
1'
#2980
0'
#2985
1!
1'
#2990
0'
#2995
0!
b1100 :
1'
#3000
0'
#3005
1!
1'
#3010
0'
#3015
0!
b1101 :
1'
#3020
0'
#3025
1!
1'
#3030
0'
#3035
0!
b1110 :
1'
#3040
0'
#3045
1!
1'
#3050
0'
#3055
0!
b1111 :
1'
#3060
0'
#3065
1!
1'
#3070
0'
#3075
0!
1"
b10100101 &
b10100101 /
b10100101 <
b0 =
1'
#3080
0'
#3085
0%
11
0"
1!
b1 2
b1 8
17
1'
#3090
0'
#3095
0!
1'
#3100
0'
#3105
1!
1'
#3110
0'
#3115
0!
1'
#3120
0'
#3125
1!
1'
#3130
0'
#3135
0!
1'
#3140
0'
#3145
1!
1'
#3150
0'
#3155
0!
1'
#3160
0'
#3165
1!
1'
#3170
0'
#3175
0!
1'
#3180
0'
#3185
1!
1'
#3190
0'
#3195
0!
1'
#3200
0'
#3205
1!
1'
#3210
0'
#3215
0!
1'
#3220
0'
#3225
1!
1'
#3230
0'
1)
#3235
1%
01
0!
b1 5
b10100101 #
b10100101 3
b0 2
07
1'
#3240
0'
#3245
1!
16
1'
#3250
0'
#3255
0!
1'
#3260
0'
#3265
1!
1'
#3270
0'
#3275
0!
1'
#3280
0'
#3285
1!
1'
#3290
0'
#3295
0!
1'
#3300
0'
#3305
1!
1'
#3310
0'
#3315
0!
1'
#3320
0'
#3325
1!
1'
#3330
0'
#3335
0!
1'
#3340
0'
#3345
1!
1'
#3350
0'
#3355
0!
1'
#3360
0'
#3365
1!
1'
#3370
0'
#3375
0!
1'
#3380
0'
#3385
1!
1'
#3390
0'
#3395
0!
1'
#3400
0'
#3405
1!
1'
#3410
0'
#3415
0!
1'
#3420
0'
#3425
1!
1'
#3430
0'
#3435
0!
1'
#3440
0'
#3445
1!
1'
#3450
0'
#3455
0!
1'
#3460
0'
#3465
1!
1'
#3470
0'
#3475
0!
1'
#3480
0'
#3485
1!
1'
#3490
0'
#3495
0!
1'
#3500
0'
#3505
1!
1'
#3510
0'
#3515
0!
1'
#3520
0'
#3525
1!
1'
#3530
0'
#3535
0!
1'
#3540
0'
#3545
1!
1'
