Verilog/4bits_shiftregister/Enhanced_4bits_shiftregister/TESTER.v
module tester(
    // Inputs
    output reg CLK,
    output reg ENB,
    output reg DIR,
    output reg S_IN,
    output reg [1:0] MODO,
    output reg [3:0] D,
    // Outputs
    input [3:0] Q,
    input S_OUT
);

// CLK generator logic
initial begin
    CLK = 0;
end
always begin
    #1 CLK <= !CLK;
    
end

initial begin
    // Display
    $dumpfile("Test_4bits_shiftregister.vcd");
    $dumpvars(0, testbench);
    $display("\t\t------------------------------------------");
    $display("\t\tTime\| clk \|  DIR  \|  S_IN \|  MODO  \| S_OUT");
    $display("\t\t------------------------------------------");
    $monitor( $time, "|\t%b |\t%b |\t%b |\t%b |\t%b ", CLK, DIR, S_IN, MODO, S_OUT);

    ENB = 0;
    #8
    ENB = 1;
    //////////////////
    // RESET PRETEST//
    //////////////////
    // Delay to complete 1 period
    #2
    // RESET MODE ON
    MODO[1:0] = 2'b11;
    // Delay to complete 1 period
    #2

    //////////////////////////
    // TEST 1: Left ROTATION//
    //////////////////////////
    // PARALEL INITIAL
    MODO[1:0] = 2'b10;
    // Left direction
    DIR = 1'b0;
    S_IN = 1'b1;
    D[3:0] = 4'b0000;
    // Delay to complete 4 period
    #10
    // Shift
    MODO[1:0] = 2'b00;
    // Delay to complete 4 period
    #10

    ///////////////////////////////////
    ////////////// RESET ////////////// 
    ///////////////////////////////////
    // RESET MODE ON
    MODO[1:0] = 2'b11;
    // Delay to complete 1 period
    #2

    ///////////////////////////
    // TEST 2: Right ROTATION//
    ///////////////////////////
    // PARALEL INITIAL after reset 
    MODO[1:0] = 2'b10;
    #10
    // Right direction
    DIR = 1'b1;
    S_IN = 1'b1;
    #2
    // Shift
    MODO[1:0] = 2'b00;
    // Delay to complete 4 period
    #10

    ///////////////////////////////////
    ////////////// RESET ////////////// 
    ///////////////////////////////////
    // RESET MODE ON
    MODO[1:0] = 2'b11;
    // Delay to complete 1 period
    #2

    ///////////////////////////////////
    // TEST 3: CIRCULAR LEFT ROTATION//
    ///////////////////////////////////
    // PARALEL INITIAL
    MODO[1:0] = 2'b10;
    #2
    D[3:0] = 4'b1010;
    // Delay to complete 4 period
    #10
    // CIRCULAR LEFT
    DIR = 1'b0;
    MODO[1:0] = 2'b01;
    #10

    ///////////////////////////////////
    ////////////// RESET ////////////// 
    ///////////////////////////////////
    // RESET MODE ON
    MODO[1:0] = 2'b11;
    // Delay to complete 1 period
    #2

    ///////////////////////////////////
    // TEST 4: CIRCULAR RIGHT ROTATION//
    ///////////////////////////////////
    // PARALEL INITIAL
    MODO[1:0] = 2'b10;
    #2
    D[3:0] = 4'b1010;
    // Delay to complete 4 period
    #10
    // CIRCULAR RIGHT
    DIR = 1'b1;
    MODO[1:0] = 2'b01;
    #10

    ///////////////////////////////////
    ////////////// RESET ////////////// 
    ///////////////////////////////////
    // RESET MODE ON
    MODO[1:0] = 2'b11;
    // Delay to complete 1 period
    #2

    ///////////////////
    // TEST 5:PARALEL//
    ///////////////////
    // PARALEL INITIAL
    MODO[1:0] = 2'b10;
    #2
    DIR = 1'b1; 
    D[3:0] = 4'b0000;
    #10
    DIR = 1'b0; 
    D[3:0] = 4'b1111;
    #10
    ENB = 0;
    #300 
    $finish;
end


endmodule

Verilog/4bits_shiftregister/Enhanced_4bits_shiftregister/4bits_shiftregister.v
module register(
    // CLK
    input CLK,
    // Transactions enabled
    input ENB,
    // Direction for the rotation
    input DIR,
    // Serial entry
    input S_IN,
    // MODE 
    input [1:0] MODO,
    // Paralel entry
    input [3:0] D,
    // Paralel output
    output reg [3:0] Q,
    // Serial output
    output reg S_OUT
);
// Params for FSM
localparam SHIFT = 2'b00;
localparam CIRCULAR_SHIFT = 2'b01;
localparam PARALEL = 2'b10;
localparam RESET = 2'b11;
// Using cases to compare results
always @(posedge CLK) begin
    if (!ENB) begin
        // IDLE
        Q <= Q;
        S_OUT <= S_OUT;
    end else begin
        case(MODO)
            // Shift
            SHIFT: begin
                if (!DIR) begin
                    // Left
                    S_OUT <= Q[3];
                    Q <= {Q[2:0], S_IN};
                end else begin
                    // Right
                    S_OUT <= Q[0];
                    Q <= {S_IN, Q[3:1]};                   
                end
            end
            // Circular Shift
            CIRCULAR_SHIFT: begin
                if (!DIR) begin
                    // Left
                    Q[3:0] <= {Q[2:0], Q[3]};
                    S_OUT <= 1'b0;
                end else begin
                    // Right
                    Q[3:0] <= {Q[0], Q[3:1]};
                    S_OUT <= 1'b0;
                end
            end
            // Paralel load
            PARALEL: begin
                Q[3:0] <= D[3:0];
                S_OUT <= 1'b0;
            end
            // RESET
            RESET: begin
                S_OUT <= 1'b0;
            end
            // Default IDLE
            default: begin
                // IDLE
                Q <= Q;
                S_OUT <= S_OUT;               
            end
        endcase
    end
end

endmodule

Verilog/4bits_shiftregister/Enhanced_4bits_shiftregister/DUT.v
`include "4bits_shiftregister.v"

module DUT(
    // CLK
    input CLK,
    // Transactions enabled
    input ENB,
    // Direction for the rotation
    input DIR,
    // Serial entry
    input S_IN,
    // MODE 
    input [1:0] MODO,
    // Paralel entry
    input [3:0] D,
    // Paralel output
    output wire [3:0] Q,
    // Serial output
    output wire S_OUT
);

register Tested_circuit(
    .CLK(CLK),
    .ENB(ENB),
    .DIR(DIR),
    .S_IN(S_IN),
    .MODO(MODO),
    .D(D),
    .Q(Q),
    .S_OUT(S_OUT)      
);



endmodule

Verilog/4bits_shiftregister/Enhanced_4bits_shiftregister/TESTBENCH.v
`include "DUT.v"
`include "TESTER.v"

module testbench;

// Cables to connect DUT and TESTER
wire CLK, ENB, DIR, S_IN, S_OUT;
wire [1:0] MODO;
wire [3:0] D;
wire [3:0] Q;

DUT DUT1(
    .CLK(CLK),
    .ENB(ENB),
    .DIR(DIR),
    .S_IN(S_IN),
    .MODO(MODO),
    .D(D),
    .Q(Q),
    .S_OUT(S_OUT)  
);

tester TESTER(
    .CLK(CLK),
    .ENB(ENB),
    .DIR(DIR),
    .S_IN(S_IN),
    .MODO(MODO),
    .D(D),
    .Q(Q),
    .S_OUT(S_OUT)
);


endmodule

Verilog/4bits_shiftregister/Enhanced_4bits_shiftregister/Test_4bits_shiftregister.vcd
$date
	Sun Mar 16 14:41:25 2025
$end
$version
	Icarus Verilog
$end
$timescale
	1s
$end
$scope module testbench $end
$var wire 1 ! S_OUT $end
$var wire 1 " S_IN $end
$var wire 4 # Q [3:0] $end
$var wire 2 $ MODO [1:0] $end
$var wire 1 % ENB $end
$var wire 1 & DIR $end
$var wire 4 ' D [3:0] $end
$var wire 1 ( CLK $end
$scope module DUT1 $end
$var wire 1 ! S_OUT $end
$var wire 1 " S_IN $end
$var wire 4 ) Q [3:0] $end
$var wire 2 * MODO [1:0] $end
$var wire 1 % ENB $end
$var wire 1 & DIR $end
$var wire 4 + D [3:0] $end
$var wire 1 ( CLK $end
$scope module Tested_circuit $end
$var wire 1 " S_IN $end
$var wire 2 , MODO [1:0] $end
$var wire 1 % ENB $end
$var wire 1 & DIR $end
$var wire 4 - D [3:0] $end
$var wire 1 ( CLK $end
$var reg 4 . Q [3:0] $end
$var reg 1 ! S_OUT $end
$upscope $end
$upscope $end
$scope module TESTER $end
$var wire 4 / Q [3:0] $end
$var wire 1 ! S_OUT $end
$var reg 1 ( CLK $end
$var reg 4 0 D [3:0] $end
$var reg 1 & DIR $end
$var reg 1 % ENB $end
$var reg 2 1 MODO [1:0] $end
$var reg 1 " S_IN $end
$upscope $end
$upscope $end
$enddefinitions $end
#0
$dumpvars
bx 1
bx 0
bx /
bx .
bx -
bx ,
bx +
bx *
bx )
0(
bx '
x&
0%
bx $
bx #
x"
x!
$end
#1
1(
#2
0(
#3
1(
#4
0(
#5
1(
#6
0(
#7
1(
#8
0(
1%
#9
1(
#10
0(
b11 $
b11 *
b11 ,
b11 1
#11
0!
1(
#12
0(
b0 '
b0 +
b0 -
b0 0
1"
0&
b10 $
b10 *
b10 ,
b10 1
#13
b0 #
b0 )
b0 .
b0 /
1(
#14
0(
#15
1(
#16
0(
#17
1(
#18
0(
#19
1(
#20
0(
#21
1(
#22
0(
b0 $
b0 *
b0 ,
b0 1
#23
b1 #
b1 )
b1 .
b1 /
1(
#24
0(
#25
b11 #
b11 )
b11 .
b11 /
1(
#26
0(
#27
b111 #
b111 )
b111 .
b111 /
1(
#28
0(
#29
b1111 #
b1111 )
b1111 .
b1111 /
1(
#30
0(
#31
1!
1(
#32
0(
b11 $
b11 *
b11 ,
b11 1
#33
0!
1(
#34
0(
b10 $
b10 *
b10 ,
b10 1
#35
b0 #
b0 )
b0 .
b0 /
1(
#36
0(
#37
1(
#38
0(
#39
1(
#40
0(
#41
1(
#42
0(
#43
1(
#44
0(
1&
#45
1(
#46
0(
b0 $
b0 *
b0 ,
b0 1
#47
b1000 #
b1000 )
b1000 .
b1000 /
1(
#48
0(
#49
b1100 #
b1100 )
b1100 .
b1100 /
1(
#50
0(
#51
b1110 #
b1110 )
b1110 .
b1110 /
1(
#52
0(
#53
b1111 #
b1111 )
b1111 .
b1111 /
1(
#54
0(
#55
1!
1(
#56
0(
b11 $
b11 *
b11 ,
b11 1
#57
0!
1(
#58
0(
b10 $
b10 *
b10 ,
b10 1
#59
b0 #
b0 )
b0 .
b0 /
1(
#60
0(
b1010 '
b1010 +
b1010 -
b1010 0
#61
b1010 #
b1010 )
b1010 .
b1010 /
1(
#62
0(
#63
1(
#64
0(
#65
1(
#66
0(
#67
1(
#68
0(
#69
1(
#70
0(
b1 $
b1 *
b1 ,
b1 1
0&
#71
b101 #
b101 )
b101 .
b101 /
1(
#72
0(
#73
b1010 #
b1010 )
b1010 .
b1010 /
1(
#74
0(
#75
b101 #
b101 )
b101 .
b101 /
1(
#76
0(
#77
b1010 #
b1010 )
b1010 .
b1010 /
1(
#78
0(
#79
b101 #
b101 )
b101 .
b101 /
1(
#80
0(
b11 $
b11 *
b11 ,
b11 1
#81
1(
#82
0(
b10 $
b10 *
b10 ,
b10 1
#83
b1010 #
b1010 )
b1010 .
b1010 /
1(
#84
0(
#85
1(
#86
0(
#87
1(
#88
0(
#89
1(
#90
0(
#91
1(
#92
0(
#93
1(
#94
0(
b1 $
b1 *
b1 ,
b1 1
1&
#95
b101 #
b101 )
b101 .
b101 /
1(
#96
0(
#97
b1010 #
b1010 )
b1010 .
b1010 /
1(
#98
0(
#99
b101 #
b101 )
b101 .
b101 /
1(
#100
0(
#101
b1010 #
b1010 )
b1010 .
b1010 /
1(
#102
0(
#103
b101 #
b101 )
b101 .
b101 /
1(
#104
0(
b11 $
b11 *
b11 ,
b11 1
#105
1(
#106
0(
b10 $
b10 *
b10 ,
b10 1
#107
b1010 #
b1010 )
b1010 .
b1010 /
1(
#108
0(
b0 '
b0 +
b0 -
b0 0
#109
b0 #
b0 )
b0 .
b0 /
1(
#110
0(
#111
1(
#112
0(
#113
1(
#114
0(
#115
1(
#116
0(
#117
1(
#118
0(
b1111 '
b1111 +
b1111 -
b1111 0
0&
#119
b1111 #
b1111 )
b1111 .
b1111 /
1(
#120
0(
#121
1(
#122
0(
#123
1(
#124
0(
#125
1(
#126
0(
#127
1(
#128
0(
0%
